Workbook

Sheet Cover
A2: Lumenpath Software, Inc.
A4: Workflow software for midsize finance teams
A6: Fiscal years covered: FY2023, FY2024, FY2025
A8: Industry: Business software (software as a service)
A9: Role fit: FP&A, Corporate finance, Revenue analysis
A11: Fictional company. All figures are illustrative and were built for this portfolio.
A12: Prepared by George Murad
A14: Contents
A15: Cover
A16: Assumptions
A17: Income Statement
A18: Balance Sheet
... A28: Formula, pulls from another sheet

Sheet Assumptions
A1: Lumenpath Software, Inc.
A2: Assumptions
A3: ($ in thousands)
B5: FY2023 | C5: FY2024 | D5: FY2025
A6: Beginning ARR, FY2023 | B6: 38000
A7: New customer ARR | B7: 12500 | C7: 15200 | D7: 16900
A8: Expansion ARR | B8: 6800 | C8: 9100 | D8: 11800
A9: Contraction ARR | B9: 1900 | C9: 2400 | D9: 2900
A10: Churned ARR | B10: 3400 | C10: 4300 | D10: 5200
A11: Beginning customers, FY2023 | B11: 830
A12: New customers | B12: 380 | C12: 420 | D12: 440
A13: Lost customers | B13: 170 | C13: 150 | D13: 160
A14: Cost of subscription, % of subscription revenue | B14: 0.18
A15: Cost of services, % of services revenue | B15: 0.85
A16: Professional services, % of subscription revenue | B16: 0.08
A17: Sales and marketing, % of total revenue | B17: 0.52 | C17: 0.47 | D17: 0.43
A18: Research and development, % of total revenue | B18: 0.28 | C18: 0.26 | D18: 0.24
A19: General and administrative, % of total revenue | B19: 0.16 | C19: 0.14 | D19: 0.12
A20: Stock based compensation, % of revenue | B20: 0.06
A21: Depreciation and amortization, % of revenue | B21: 0.022
A22: Capital expenditures, % of revenue | B22: 0.025
A23: Interest income rate on beginning cash | B23: 0.03
A24: Income tax expense, flat per year | B24: 150
A25: Accounts receivable days (DSO) | B25: 62 | C25: 60 | D25: 58
A26: Prepaid and other, % of revenue | B26: 0.04
A27: Accounts payable, % of cost of revenue plus opex | B27: 0.035
A28: Accrued expenses, % of operating expenses | B28: 0.11
A29: Deferred revenue, % of ending ARR | B29: 0.45
A30: Opening balance sheet FY2022: Cash | B30: 62000
A31: Opening balance sheet FY2022: Accounts receivable | B31: 9800
A32: Opening balance sheet FY2022: Prepaid and other | B32: 2100
A33: Opening balance sheet FY2022: Property and capitalized software, net | B33: 5500
A34: Opening balance sheet FY2022: Accounts payable | B34: 2300
A35: Opening balance sheet FY2022: Accrued expenses | B35: 6900
A36: Opening balance sheet FY2022: Deferred revenue | B36: 17000
A37: Opening balance sheet FY2022: Common stock and paid in capital | B37: 145000
A38: Opening balance sheet FY2022: Accumulated deficit | B38: -91800

Sheet Income Statement
A1: Lumenpath Software, Inc.
A2: Income Statement
A3: ($ in thousands) For the years ended December 31
B5: FY2023 | C5: FY2024 | D5: FY2025
A6: Subscription | B6: =(('Assumptions'!B6+(((('Assumptions'!B6+'Assumptions'!B7)+'Assumptions'!B8)-'Assumptions'!B9)-'Assumptions'!B10))/2) -> 45000 | C6: =(((((('Assumptions'!B6+'Assumptions'!B7)+'Assumptions'!B8)-'Assumptions'!B9)-'Assumptions'!B10)+(((((((('Assumptions'!B6+'Assumptions'!B7)+'Assumptions'!B8)-'Assumptions'!B9)-'Assumptions'!B10)+'Assumptions'!C7)+'Assumptions'!C8)-'Assumptions'!C9)-'Assumptions'!C10))/2) -> 60800 | D6: =(((((((((('Assumptions'!B6+'Assumptions'!B7)+'Assumptions'!B8)-'Assumptions'!B9)-'Assumptions'!B10)+'Assumptions'!C7)+'Assumptions'!C8)-'Assumptions'!C9)-'Assumptions'!C10)+(((((((((((('Assumptions'!B6+'Assumptions'!B7)+'Assumptions'!B8)-'Assumptions'!B9)-'Assumptions'!B10)+'Assumptions'!C7)+'Assumptions'!C8)-'Assumptions'!C9)-'Assumptions'!C10)+'Assumptions'!D7)+'Assumptions'!D8)-'Assumptions'!D9)-'Assumptions'!D10))/2) -> 79900
A7: Professional services | B7: =(B6*'Assumptions'!B16) -> 3600 | C7: =(C6*'Assumptions'!B16) -> 4864 | D7: =(D6*'Assumptions'!B16) -> 6392
A8: Total revenue | B8: =(B6+B7) -> 48600 | C8: =(C6+C7) -> 65664 | D8: =(D6+D7) -> 86292
A9: Cost of subscription | B9: =(B6*'Assumptions'!B14) -> 8100 | C9: =(C6*'Assumptions'!B14) -> 10944 | D9: =(D6*'Assumptions'!B14) -> 14382
A10: Cost of services | B10: =(B7*'Assumptions'!B15) -> 3060 | C10: =(C7*'Assumptions'!B15) -> 4134.4 | D10: =(D7*'Assumptions'!B15) -> 5433.2
A11: Gross profit | B11: =((B8-B9)-B10) -> 37440 | C11: =((C8-C9)-C10) -> 50585.6 | D11: =((D8-D9)-D10) -> 66476.8
A12: Sales and marketing | B12: =(B8*'Assumptions'!B17) -> 25272 | C12: =(C8*'Assumptions'!C17) -> 30862.08 | D12: =(D8*'Assumptions'!D17) -> 37105.56
A13: Research and development | B13: =(B8*'Assumptions'!B18) -> 13608 | C13: =(C8*'Assumptions'!C18) -> 17072.64 | D13: =(D8*'Assumptions'!D18) -> 20710.08
A14: General and administrative | B14: =(B8*'Assumptions'!B19) -> 7776 | C14: =(C8*'Assumptions'!C19) -> 9192.96 | D14: =(D8*'Assumptions'!D19) -> 10355.04
A15: Total operating expenses | B15: =((B12+B13)+B14) -> 46656 | C15: =((C12+C13)+C14) -> 57127.68 | D15: =((D12+D13)+D14) -> 68170.68
A16: Operating income (loss) | B16: =(B11-B15) -> -9216 | C16: =(C11-C15) -> -6542.08 | D16: =(D11-D15) -> -1693.88
A17: Interest income | B17: =('Assumptions'!B30*'Assumptions'!B23) -> 1860 | C17: =('Balance Sheet'!B7*'Assumptions'!B23) -> 1899.6173 | D17: =('Balance Sheet'!C7*'Assumptions'!B23) -> 2058.756
A18: Income before taxes | B18: =(B16+B17) -> -7356 | C18: =(C16+C17) -> -4642.4627 | D18: =(D16+D17) -> 364.87602
A19: Income tax expense | B19: ='Assumptions'!B24 -> 150 | C19: ='Assumptions'!B24 -> 150 | D19: ='Assumptions'!B24 -> 150
A20: Net income (loss) | B20: =(B18-B19) -> -7506 | C20: =(C18-C19) -> -4792.4627 | D20: =(D18-D19) -> 214.87602
A21: Gross margin | B21: =(B11/B8) -> 0.77037037 | C21: =(C11/C8) -> 0.77037037 | D21: =(D11/D8) -> 0.77037037
A22: Operating margin | B22: =(B16/B8) -> -0.18962963 | C22: =(C16/C8) -> -0.09962963 | D22: =(D16/D8) -> -0.01962963
A23: Stock based compensation | B23: =(B8*'Assumptions'!B20) -> 2916 | C23: =(C8*'Assumptions'!B20) -> 3939.84 | D23: =(D8*'Assumptions'!B20) -> 5177.52
A24: Depreciation and amortization | B24: =(B8*'Assumptions'!B21) -> 1069.2 | C24: =(C8*'Assumptions'!B21) -> 1444.608 | D24: =(D8*'Assumptions'!B21) -> 1898.424
A25: Adjusted EBITDA | B25: =((B16+B24)+B23) -> -5230.8 | C25: =((C16+C24)+C23) -> -1157.632 | D25: =((D16+D24)+D23) -> 5382.064

Sheet Balance Sheet
A1: Lumenpath Software, Inc.
A2: Balance Sheet
A3: ($ in thousands) As of December 31
B5: FY2023 | C5: FY2024 | D5: FY2025
A6: Assets
A7: Cash and cash equivalents | B7: ='Cash Flow'!B19 -> 63320.578 | C7: ='Cash Flow'!C19 -> 68625.201 | D7: ='Cash Flow'!D19 -> 81052.553
A8: Accounts receivable | B8: =(('Income Statement'!B8*'Assumptions'!B25)/365) -> 8255.3425 | C8: =(('Income Statement'!C8*'Assumptions'!C25)/365) -> 10794.082 | D8: =(('Income Statement'!D8*'Assumptions'!D25)/365) -> 13712.153
A9: Prepaid and other | B9: =('Income Statement'!B8*'Assumptions'!B26) -> 1944 | C9: =('Income Statement'!C8*'Assumptions'!B26) -> 2626.56 | D9: =('Income Statement'!D8*'Assumptions'!B26) -> 3451.68
A10: Total current assets | B10: =(B7+B8+B9) -> 73519.92 | C10: =(C7+C8+C9) -> 82045.843 | D10: =(D7+D8+D9) -> 98216.386
A11: Property and capitalized software, net | B11: =(('Assumptions'!B33+('Income Statement'!B8*'Assumptions'!B22))-'Income Statement'!B24) -> 5645.8 | C11: =((B11+('Income Statement'!C8*'Assumptions'!B22))-'Income Statement'!C24) -> 5842.792 | D11: =((C11+('Income Statement'!D8*'Assumptions'!B22))-'Income Statement'!D24) -> 6101.668
A12: Total assets | B12: =(B10+B11) -> 79165.72 | C12: =(C10+C11) -> 87888.635 | D12: =(D10+D11) -> 104318.05
A13: Liabilities
A14: Accounts payable | B14: =((('Income Statement'!B9+'Income Statement'!B10)+'Income Statement'!B15)*'Assumptions'!B27) -> 2023.56 | C14: =((('Income Statement'!C9+'Income Statement'!C10)+'Income Statement'!C15)*'Assumptions'!B27) -> 2527.2128 | D14: =((('Income Statement'!D9+'Income Statement'!D10)+'Income Statement'!D15)*'Assumptions'!B27) -> 3079.5058
A15: Accrued expenses | B15: =('Income Statement'!B15*'Assumptions'!B28) -> 5132.16 | C15: =('Income Statement'!C15*'Assumptions'!B28) -> 6284.0448 | D15: =('Income Statement'!D15*'Assumptions'!B28) -> 7498.7748
A16: Deferred revenue | B16: =((((('Assumptions'!B6+'Assumptions'!B7)+'Assumptions'!B8)-'Assumptions'!B9)-'Assumptions'!B10)*'Assumptions'!B29) -> 23400 | C16: =((((((((('Assumptions'!B6+'Assumptions'!B7)+'Assumptions'!B8)-'Assumptions'!B9)-'Assumptions'!B10)+'Assumptions'!C7)+'Assumptions'!C8)-'Assumptions'!C9)-'Assumptions'!C10)*'Assumptions'!B29) -> 31320 | D16: =((((((((((((('Assumptions'!B6+'Assumptions'!B7)+'Assumptions'!B8)-'Assumptions'!B9)-'Assumptions'!B10)+'Assumptions'!C7)+'Assumptions'!C8)-'Assumptions'!C9)-'Assumptions'!C10)+'Assumptions'!D7)+'Assumptions'!D8)-'Assumptions'!D9)-'Assumptions'!D10)*'Assumptions'!B29) -> 40590
A17: Total liabilities | B17: =(B14+B15+B16) -> 30555.72 | C17: =(C14+C15+C16) -> 40131.258 | D17: =(D14+D15+D16) -> 51168.281
A18: Equity
A19: Common stock and paid in capital | B19: =('Assumptions'!B37+'Income Statement'!B23) -> 147916 | C19: =(B19+'Income Statement'!C23) -> 151855.84 | D19: =(C19+'Income Statement'!D23) -> 157033.36
A20: Accumulated deficit | B20: =('Assumptions'!B38+'Income Statement'!B20) -> -99306 | C20: =(B20+'Income Statement'!C20) -> -104098.46 | D20: =(C20+'Income Statement'!D20) -> -103883.59
A21: Total equity | B21: =(B19+B20) -> 48610 | C21: =(C19+C20) -> 47757.377 | D21: =(D19+D20) -> 53149.773
A22: Total liabilities and equity | B22: =(B17+B21) -> 79165.72 | C22: =(C17+C21) -> 87888.635 | D22: =(D17+D21) -> 104318.05

Sheet Cash Flow
A1: Lumenpath Software, Inc.
A2: Cash Flow Statement
A3: ($ in thousands) For the years ended December 31
B5: FY2023 | C5: FY2024 | D5: FY2025
A6: Net income (loss) | B6: ='Income Statement'!B20 -> -7506 | C6: ='Income Statement'!C20 -> -4792.4627 | D6: ='Income Statement'!D20 -> 214.87602
A7: Depreciation and amortization | B7: ='Income Statement'!B24 -> 1069.2 | C7: ='Income Statement'!C24 -> 1444.608 | D7: ='Income Statement'!D24 -> 1898.424
A8: Stock based compensation | B8: ='Income Statement'!B23 -> 2916 | C8: ='Income Statement'!C23 -> 3939.84 | D8: ='Income Statement'!D23 -> 5177.52
A9: (Increase) decrease in accounts receivable | B9: =(-('Balance Sheet'!B8-'Assumptions'!B31)) -> 1544.6575 | C9: =(-('Balance Sheet'!C8-'Balance Sheet'!B8)) -> -2538.7397 | D9: =(-('Balance Sheet'!D8-'Balance Sheet'!C8)) -> -2918.0712
A10: (Increase) decrease in prepaid and other | B10: =(-('Balance Sheet'!B9-'Assumptions'!B32)) -> 156 | C10: =(-('Balance Sheet'!C9-'Balance Sheet'!B9)) -> -682.56 | D10: =(-('Balance Sheet'!D9-'Balance Sheet'!C9)) -> -825.12
A11: Increase (decrease) in accounts payable | B11: =('Balance Sheet'!B14-'Assumptions'!B34) -> -276.44 | C11: =('Balance Sheet'!C14-'Balance Sheet'!B14) -> 503.6528 | D11: =('Balance Sheet'!D14-'Balance Sheet'!C14) -> 552.293
A12: Increase (decrease) in accrued expenses | B12: =('Balance Sheet'!B15-'Assumptions'!B35) -> -1767.84 | C12: =('Balance Sheet'!C15-'Balance Sheet'!B15) -> 1151.8848 | D12: =('Balance Sheet'!D15-'Balance Sheet'!C15) -> 1214.73
A13: Increase (decrease) in deferred revenue | B13: =('Balance Sheet'!B16-'Assumptions'!B36) -> 6400 | C13: =('Balance Sheet'!C16-'Balance Sheet'!B16) -> 7920 | D13: =('Balance Sheet'!D16-'Balance Sheet'!C16) -> 9270
A14: Cash from operating activities | B14: =(B6+B7+B8+B9+B10+B11+B12+B13) -> 2535.5775 | C14: =(C6+C7+C8+C9+C10+C11+C12+C13) -> 6946.2232 | D14: =(D6+D7+D8+D9+D10+D11+D12+D13) -> 14584.652
A15: Capital expenditures | B15: =((-'Income Statement'!B8)*'Assumptions'!B22) -> -1215 | C15: =((-'Income Statement'!C8)*'Assumptions'!B22) -> -1641.6 | D15: =((-'Income Statement'!D8)*'Assumptions'!B22) -> -2157.3
A16: Cash from investing activities | B16: =B15 -> -1215 | C16: =C15 -> -1641.6 | D16: =D15 -> -2157.3
A17: Net change in cash | B17: =(B14+B16) -> 1320.5775 | C17: =(C14+C16) -> 5304.6232 | D17: =(D14+D16) -> 12427.352
A18: Beginning cash | B18: ='Assumptions'!B30 -> 62000 | C18: ='Balance Sheet'!B7 -> 63320.578 | D18: ='Balance Sheet'!C7 -> 68625.201
A19: Ending cash | B19: =(B18+B17) -> 63320.578 | C19: =(C18+C17) -> 68625.201 | D19: =(D18+D17) -> 81052.553

Sheet Ratios
A1: Lumenpath Software, Inc.
A2: Ratios
A3: ($ in thousands)
B5: FY2023 | C5: FY2024 | D5: FY2025
A6: Gross margin | B6: =('Income Statement'!B11/'Income Statement'!B8) -> 0.77037037 | C6: =('Income Statement'!C11/'Income Statement'!C8) -> 0.77037037 | D6: =('Income Statement'!D11/'Income Statement'!D8) -> 0.77037037
A7: Operating margin | B7: =('Income Statement'!B16/'Income Statement'!B8) -> -0.18962963 | C7: =('Income Statement'!C16/'Income Statement'!C8) -> -0.09962963 | D7: =('Income Statement'!D16/'Income Statement'!D8) -> -0.01962963
A8: Adjusted EBITDA margin | B8: =('Income Statement'!B25/'Income Statement'!B8) -> -0.10762963 | C8: =('Income Statement'!C25/'Income Statement'!C8) -> -0.01762963 | D8: =('Income Statement'!D25/'Income Statement'!D8) -> 0.06237037
A9: Net margin | B9: =('Income Statement'!B20/'Income Statement'!B8) -> -0.15444444 | C9: =('Income Statement'!C20/'Income Statement'!C8) -> -0.072984629 | D9: =('Income Statement'!D20/'Income Statement'!D8) -> 0.0024901036
A10: Revenue growth | B10: n/a | C10: =(('Income Statement'!C8/'Income Statement'!B8)-1) -> 0.35111111 | D10: =(('Income Statement'!D8/'Income Statement'!C8)-1) -> 0.31414474
A11: Current ratio | B11: =('Balance Sheet'!B10/'Balance Sheet'!B17) -> 2.4060935 | C11: =('Balance Sheet'!C10/'Balance Sheet'!C17) -> 2.0444374 | D11: =('Balance Sheet'!D10/'Balance Sheet'!D17) -> 1.9194779
A12: Return on equity | B12: =('Income Statement'!B20/((('Assumptions'!B37+'Assumptions'!B38)+'Balance Sheet'!B21)/2)) -> -0.14745113 | C12: =('Income Statement'!C20/(('Balance Sheet'!B21+'Balance Sheet'!C21)/2)) -> -0.099462345 | D12: =('Income Statement'!D20/(('Balance Sheet'!C21+'Balance Sheet'!D21)/2)) -> 0.0042588859
A13: Days sales outstanding | B13: =(('Balance Sheet'!B8/'Income Statement'!B8)*365) -> 62 | C13: =(('Balance Sheet'!C8/'Income Statement'!C8)*365) -> 60 | D13: =(('Balance Sheet'!D8/'Income Statement'!D8)*365) -> 58
A14: Free cash flow | B14: =('Cash Flow'!B14+'Cash Flow'!B15) -> 1320.5775 | C14: =('Cash Flow'!C14+'Cash Flow'!C15) -> 5304.6232 | D14: =('Cash Flow'!D14+'Cash Flow'!D15) -> 12427.352
A15: FCF margin | B15: =(('Cash Flow'!B14+'Cash Flow'!B15)/'Income Statement'!B8) -> 0.027172377 | C15: =(('Cash Flow'!C14+'Cash Flow'!C15)/'Income Statement'!C8) -> 0.080784345 | D15: =(('Cash Flow'!D14+'Cash Flow'!D15)/'Income Statement'!D8) -> 0.14401511

Sheet SaaS Metrics
A1: Lumenpath Software, Inc.
A2: Recurring revenue and unit economics: ARR bridge
A3: ($ in thousands)
B5: FY2023 | C5: FY2024 | D5: FY2025
A6: Beginning ARR | B6: ='Assumptions'!B6 -> 38000 | C6: =(((('Assumptions'!B6+'Assumptions'!B7)+'Assumptions'!B8)-'Assumptions'!B9)-'Assumptions'!B10) -> 52000 | D6: =(((((((('Assumptions'!B6+'Assumptions'!B7)+'Assumptions'!B8)-'Assumptions'!B9)-'Assumptions'!B10)+'Assumptions'!C7)+'Assumptions'!C8)-'Assumptions'!C9)-'Assumptions'!C10) -> 69600
A7: New customer ARR | B7: ='Assumptions'!B7 -> 12500 | C7: ='Assumptions'!C7 -> 15200 | D7: ='Assumptions'!D7 -> 16900
A8: Expansion ARR | B8: ='Assumptions'!B8 -> 6800 | C8: ='Assumptions'!C8 -> 9100 | D8: ='Assumptions'!D8 -> 11800
A9: Contraction ARR | B9: ='Assumptions'!B9 -> 1900 | C9: ='Assumptions'!C9 -> 2400 | D9: ='Assumptions'!D9 -> 2900
A10: Churned ARR | B10: ='Assumptions'!B10 -> 3400 | C10: ='Assumptions'!C10 -> 4300 | D10: ='Assumptions'!D10 -> 5200
A11: Ending ARR | B11: =((((B6+B7)+B8)-B9)-B10) -> 52000 | C11: =((((C6+C7)+C8)-C9)-C10) -> 69600 | D11: =((((D6+D7)+D8)-D9)-D10) -> 90200
B14: FY2023 | C14: FY2024 | D14: FY2025
A15: Ending ARR | B15: ='SaaS Metrics'!B11 -> 52000 | C15: ='SaaS Metrics'!C11 -> 69600 | D15: ='SaaS Metrics'!D11 -> 90200
A16: Net new ARR | B16: =((('SaaS Metrics'!B7+'SaaS Metrics'!B8)-'SaaS Metrics'!B9)-'SaaS Metrics'!B10) -> 14000 | C16: =((('SaaS Metrics'!C7+'SaaS Metrics'!C8)-'SaaS Metrics'!C9)-'SaaS Metrics'!C10) -> 17600 | D16: =((('SaaS Metrics'!D7+'SaaS Metrics'!D8)-'SaaS Metrics'!D9)-'SaaS Metrics'!D10) -> 20600
A17: ARR growth | B17: n/a | C17: =(('SaaS Metrics'!C11/'SaaS Metrics'!B11)-1) -> 0.33846154 | D17: =(('SaaS Metrics'!D11/'SaaS Metrics'!C11)-1) -> 0.29597701
A18: Net revenue retention | B18: =(((('SaaS Metrics'!B6+'SaaS Metrics'!B8)-'SaaS Metrics'!B9)-'SaaS Metrics'!B10)/'SaaS Metrics'!B6) -> 1.0394737 | C18: =(((('SaaS Metrics'!C6+'SaaS Metrics'!C8)-'SaaS Metrics'!C9)-'SaaS Metrics'!C10)/'SaaS Metrics'!C6) -> 1.0461538 | D18: =(((('SaaS Metrics'!D6+'SaaS Metrics'!D8)-'SaaS Metrics'!D9)-'SaaS Metrics'!D10)/'SaaS Metrics'!D6) -> 1.0531609
A19: Gross revenue retention | B19: =((('SaaS Metrics'!B6-'SaaS Metrics'!B9)-'SaaS Metrics'!B10)/'SaaS Metrics'!B6) -> 0.86052632 | C19: =((('SaaS Metrics'!C6-'SaaS Metrics'!C9)-'SaaS Metrics'!C10)/'SaaS Metrics'!C6) -> 0.87115385 | D19: =((('SaaS Metrics'!D6-'SaaS Metrics'!D9)-'SaaS Metrics'!D10)/'SaaS Metrics'!D6) -> 0.88362069
A20: Customers | B20: =(('Assumptions'!B11+'Assumptions'!B12)-'Assumptions'!B13) -> 1040 | C20: =((B20+'Assumptions'!C12)-'Assumptions'!C13) -> 1310 | D20: =((C20+'Assumptions'!D12)-'Assumptions'!D13) -> 1590
A21: Average ARR per customer | B21: =((B15/B20)*1000) -> 50000 | C21: =((C15/C20)*1000) -> 53129.771 | D21: =((D15/D20)*1000) -> 56729.56
A22: Customer churn | B22: =('Assumptions'!B13/'Assumptions'!B11) -> 0.20481928 | C22: =('Assumptions'!C13/B20) -> 0.14423077 | D22: =('Assumptions'!D13/C20) -> 0.1221374
A23: CAC payback, months | B23: =(('Income Statement'!B12/(('SaaS Metrics'!B7+'SaaS Metrics'!B8)*(1-'Assumptions'!B14)))*12) -> 19.162391 | C23: =(('Income Statement'!C12/(('SaaS Metrics'!C7+'SaaS Metrics'!C8)*(1-'Assumptions'!B14)))*12) -> 18.586016 | D23: =(('Income Statement'!D12/(('SaaS Metrics'!D7+'SaaS Metrics'!D8)*(1-'Assumptions'!B14)))*12) -> 18.920146
A24: Magic number | B24: =(((('SaaS Metrics'!B7+'SaaS Metrics'!B8)-'SaaS Metrics'!B9)-'SaaS Metrics'!B10)/'Income Statement'!B12) -> 0.55397278 | C24: =(((('SaaS Metrics'!C7+'SaaS Metrics'!C8)-'SaaS Metrics'!C9)-'SaaS Metrics'!C10)/'Income Statement'!C12) -> 0.57027913 | D24: =(((('SaaS Metrics'!D7+'SaaS Metrics'!D8)-'SaaS Metrics'!D9)-'SaaS Metrics'!D10)/'Income Statement'!D12) -> 0.55517286
A25: Customer lifetime value | B25: =((((B21/1000)*(1-'Assumptions'!B14))/B22)*1000) -> 200176.47 | C25: =((((C21/1000)*(1-'Assumptions'!B14))/C22)*1000) -> 302060.46 | D25: =((((D21/1000)*(1-'Assumptions'!B14))/D22)*1000) -> 380868.08
A26: Acquisition cost per new customer | B26: =(((0.7*'Income Statement'!B12)/'Assumptions'!B12)*1000) -> 46553.684 | C26: =(((0.7*'Income Statement'!C12)/'Assumptions'!C12)*1000) -> 51436.8 | D26: =(((0.7*'Income Statement'!D12)/'Assumptions'!D12)*1000) -> 59031.573
A27: LTV to CAC | B27: =(B25/B26) -> 4.2999061 | C27: =(C25/C26) -> 5.8724582 | D27: =(D25/D26) -> 6.4519386
A28: Rule of 40 | B28: n/a | C28: =((('Income Statement'!C8/'Income Statement'!B8)-1)+(('Cash Flow'!C14+'Cash Flow'!C15)/'Income Statement'!C8)) -> 0.43189546 | D28: =((('Income Statement'!D8/'Income Statement'!C8)-1)+(('Cash Flow'!D14+'Cash Flow'!D15)/'Income Statement'!D8)) -> 0.45815985

Sheet DCF
A1: Lumenpath Software, Inc.
A2: Discounted cash flow valuation: forecast assumptions
A3: ($ in thousands)
B5: FY2026 | C5: FY2027 | D5: FY2028 | E5: FY2029 | F5: FY2030
A6: Revenue growth | B6: 0.28 | C6: 0.24 | D6: 0.2 | E6: 0.17 | F6: 0.14
A7: FCF margin | B7: 0.16 | C7: 0.19 | D7: 0.22 | E7: 0.24 | F7: 0.25
A8: WACC | B8: 0.115
A9: Terminal growth | B9: 0.04
B12: FY2026 | C12: FY2027 | D12: FY2028 | E12: FY2029 | F12: FY2030
A13: Revenue | B13: =('Income Statement'!D8*(1+'DCF'!B6)) -> 110453.76 | C13: =(B13*(1+'DCF'!C6)) -> 136962.66 | D13: =(C13*(1+'DCF'!D6)) -> 164355.19 | E13: =(D13*(1+'DCF'!E6)) -> 192295.58 | F13: =(E13*(1+'DCF'!F6)) -> 219216.96
A14: Free cash flow | B14: =(B13*'DCF'!B7) -> 17672.602 | C14: =(C13*'DCF'!C7) -> 26022.906 | D14: =(D13*'DCF'!D7) -> 36158.143 | E14: =(E13*'DCF'!E7) -> 46150.939 | F14: =(F13*'DCF'!F7) -> 54804.24
A15: Discount factor | B15: =(1/((1+'DCF'!B8)^1)) -> 0.89686099 | C15: =(1/((1+'DCF'!B8)^2)) -> 0.80435963 | D15: =(1/((1+'DCF'!B8)^3)) -> 0.72139877 | E15: =(1/((1+'DCF'!B8)^4)) -> 0.64699441 | F15: =(1/((1+'DCF'!B8)^5)) -> 0.58026405
A16: PV of free cash flow | B16: =(B14*B15) -> 15849.867 | C16: =(C14*C15) -> 20931.775 | D16: =(D14*D15) -> 26084.44 | E16: =(E14*E15) -> 29859.4 | F16: =(F14*F15) -> 31800.93
B19: Value
A20: Sum of PV of free cash flow | B20: =('DCF'!B16+'DCF'!C16+'DCF'!D16+'DCF'!E16+'DCF'!F16) -> 124526.41
A21: Terminal value | B21: =(('DCF'!F14*(1+'DCF'!B9))/('DCF'!B8-'DCF'!B9)) -> 759952.12
A22: PV of terminal value | B22: =(B21*'DCF'!F15) -> 440972.9
A23: Enterprise value | B23: =(B20+B22) -> 565499.31
A24: Equity value | B24: =(B23+'Balance Sheet'!D7) -> 646551.86
A25: EV / FY2025 ending ARR | B25: =(B23/'SaaS Metrics'!D11) -> 6.2693936
A26: Terminal value share of EV | B26: =(B22/B23) -> 0.77979387
B29: 3.0% | C29: 3.5% | D29: 4.0% | E29: 4.5% | F29: 5.0%
A30: WACC 10.5% | B30: =(((('DCF'!B14/((1+0.105)^1))+('DCF'!C14/((1+0.105)^2))+('DCF'!D14/((1+0.105)^3))+('DCF'!E14/((1+0.105)^4))+('DCF'!F14/((1+0.105)^5)))+((('DCF'!F14*(1+0.03))/(0.105-0.03))/((1+0.105)^5)))+'Balance Sheet'!D7) -> 666233.82 | C30: =(((('DCF'!B14/((1+0.105)^1))+('DCF'!C14/((1+0.105)^2))+('DCF'!D14/((1+0.105)^3))+('DCF'!E14/((1+0.105)^4))+('DCF'!F14/((1+0.105)^5)))+((('DCF'!F14*(1+0.035))/(0.105-0.035))/((1+0.105)^5)))+'Balance Sheet'!D7) -> 701242.5 | D30: =(((('DCF'!B14/((1+0.105)^1))+('DCF'!C14/((1+0.105)^2))+('DCF'!D14/((1+0.105)^3))+('DCF'!E14/((1+0.105)^4))+('DCF'!F14/((1+0.105)^5)))+((('DCF'!F14*(1+0.04))/(0.105-0.04))/((1+0.105)^5)))+'Balance Sheet'!D7) -> 741637.13 | E30: =(((('DCF'!B14/((1+0.105)^1))+('DCF'!C14/((1+0.105)^2))+('DCF'!D14/((1+0.105)^3))+('DCF'!E14/((1+0.105)^4))+('DCF'!F14/((1+0.105)^5)))+((('DCF'!F14*(1+0.045))/(0.105-0.045))/((1+0.105)^5)))+'Balance Sheet'!D7) -> 788764.2 | F30: =(((('DCF'!B14/((1+0.105)^1))+('DCF'!C14/((1+0.105)^2))+('DCF'!D14/((1+0.105)^3))+('DCF'!E14/((1+0.105)^4))+('DCF'!F14/((1+0.105)^5)))+((('DCF'!F14*(1+0.05))/(0.105-0.05))/((1+0.105)^5)))+'Balance Sheet'!D7) -> 844459.83
A31: WACC 11.0% | B31: =(((('DCF'!B14/((1+0.11)^1))+('DCF'!C14/((1+0.11)^2))+('DCF'!D14/((1+0.11)^3))+('DCF'!E14/((1+0.11)^4))+('DCF'!F14/((1+0.11)^5)))+((('DCF'!F14*(1+0.03))/(0.11-0.03))/((1+0.11)^5)))+'Balance Sheet'!D7) -> 626199.79 | C31: =(((('DCF'!B14/((1+0.11)^1))+('DCF'!C14/((1+0.11)^2))+('DCF'!D14/((1+0.11)^3))+('DCF'!E14/((1+0.11)^4))+('DCF'!F14/((1+0.11)^5)))+((('DCF'!F14*(1+0.035))/(0.11-0.035))/((1+0.11)^5)))+'Balance Sheet'!D7) -> 656284.17 | D31: =(((('DCF'!B14/((1+0.11)^1))+('DCF'!C14/((1+0.11)^2))+('DCF'!D14/((1+0.11)^3))+('DCF'!E14/((1+0.11)^4))+('DCF'!F14/((1+0.11)^5)))+((('DCF'!F14*(1+0.04))/(0.11-0.04))/((1+0.11)^5)))+'Balance Sheet'!D7) -> 690666.31 | E31: =(((('DCF'!B14/((1+0.11)^1))+('DCF'!C14/((1+0.11)^2))+('DCF'!D14/((1+0.11)^3))+('DCF'!E14/((1+0.11)^4))+('DCF'!F14/((1+0.11)^5)))+((('DCF'!F14*(1+0.045))/(0.11-0.045))/((1+0.11)^5)))+'Balance Sheet'!D7) -> 730338.01 | F31: =(((('DCF'!B14/((1+0.11)^1))+('DCF'!C14/((1+0.11)^2))+('DCF'!D14/((1+0.11)^3))+('DCF'!E14/((1+0.11)^4))+('DCF'!F14/((1+0.11)^5)))+((('DCF'!F14*(1+0.05))/(0.11-0.05))/((1+0.11)^5)))+'Balance Sheet'!D7) -> 776621.67
A32: WACC 11.5% | B32: =(((('DCF'!B14/((1+0.115)^1))+('DCF'!C14/((1+0.115)^2))+('DCF'!D14/((1+0.115)^3))+('DCF'!E14/((1+0.115)^4))+('DCF'!F14/((1+0.115)^5)))+((('DCF'!F14*(1+0.03))/(0.115-0.03))/((1+0.115)^5)))+'Balance Sheet'!D7) -> 590931.41 | C32: =(((('DCF'!B14/((1+0.115)^1))+('DCF'!C14/((1+0.115)^2))+('DCF'!D14/((1+0.115)^3))+('DCF'!E14/((1+0.115)^4))+('DCF'!F14/((1+0.115)^5)))+((('DCF'!F14*(1+0.035))/(0.115-0.035))/((1+0.115)^5)))+'Balance Sheet'!D7) -> 617003.5 | D32: =(((('DCF'!B14/((1+0.115)^1))+('DCF'!C14/((1+0.115)^2))+('DCF'!D14/((1+0.115)^3))+('DCF'!E14/((1+0.115)^4))+('DCF'!F14/((1+0.115)^5)))+((('DCF'!F14*(1+0.04))/(0.115-0.04))/((1+0.115)^5)))+'Balance Sheet'!D7) -> 646551.86 | E32: =(((('DCF'!B14/((1+0.115)^1))+('DCF'!C14/((1+0.115)^2))+('DCF'!D14/((1+0.115)^3))+('DCF'!E14/((1+0.115)^4))+('DCF'!F14/((1+0.115)^5)))+((('DCF'!F14*(1+0.045))/(0.115-0.045))/((1+0.115)^5)))+'Balance Sheet'!D7) -> 680321.42 | F32: =(((('DCF'!B14/((1+0.115)^1))+('DCF'!C14/((1+0.115)^2))+('DCF'!D14/((1+0.115)^3))+('DCF'!E14/((1+0.115)^4))+('DCF'!F14/((1+0.115)^5)))+((('DCF'!F14*(1+0.05))/(0.115-0.05))/((1+0.115)^5)))+'Balance Sheet'!D7) -> 719286.29
A33: WACC 12.0% | B33: =(((('DCF'!B14/((1+0.12)^1))+('DCF'!C14/((1+0.12)^2))+('DCF'!D14/((1+0.12)^3))+('DCF'!E14/((1+0.12)^4))+('DCF'!F14/((1+0.12)^5)))+((('DCF'!F14*(1+0.03))/(0.12-0.03))/((1+0.12)^5)))+'Balance Sheet'!D7) -> 559633.2 | C33: =(((('DCF'!B14/((1+0.12)^1))+('DCF'!C14/((1+0.12)^2))+('DCF'!D14/((1+0.12)^3))+('DCF'!E14/((1+0.12)^4))+('DCF'!F14/((1+0.12)^5)))+((('DCF'!F14*(1+0.035))/(0.12-0.035))/((1+0.12)^5)))+'Balance Sheet'!D7) -> 582397.31 | D33: =(((('DCF'!B14/((1+0.12)^1))+('DCF'!C14/((1+0.12)^2))+('DCF'!D14/((1+0.12)^3))+('DCF'!E14/((1+0.12)^4))+('DCF'!F14/((1+0.12)^5)))+((('DCF'!F14*(1+0.04))/(0.12-0.04))/((1+0.12)^5)))+'Balance Sheet'!D7) -> 608006.93 | E33: =(((('DCF'!B14/((1+0.12)^1))+('DCF'!C14/((1+0.12)^2))+('DCF'!D14/((1+0.12)^3))+('DCF'!E14/((1+0.12)^4))+('DCF'!F14/((1+0.12)^5)))+((('DCF'!F14*(1+0.045))/(0.12-0.045))/((1+0.12)^5)))+'Balance Sheet'!D7) -> 637031.17 | F33: =(((('DCF'!B14/((1+0.12)^1))+('DCF'!C14/((1+0.12)^2))+('DCF'!D14/((1+0.12)^3))+('DCF'!E14/((1+0.12)^4))+('DCF'!F14/((1+0.12)^5)))+((('DCF'!F14*(1+0.05))/(0.12-0.05))/((1+0.12)^5)))+'Balance Sheet'!D7) -> 670201.73
A34: WACC 12.5% | B34: =(((('DCF'!B14/((1+0.125)^1))+('DCF'!C14/((1+0.125)^2))+('DCF'!D14/((1+0.125)^3))+('DCF'!E14/((1+0.125)^4))+('DCF'!F14/((1+0.125)^5)))+((('DCF'!F14*(1+0.03))/(0.125-0.03))/((1+0.125)^5)))+'Balance Sheet'!D7) -> 531677.21 | C34: =(((('DCF'!B14/((1+0.125)^1))+('DCF'!C14/((1+0.125)^2))+('DCF'!D14/((1+0.125)^3))+('DCF'!E14/((1+0.125)^4))+('DCF'!F14/((1+0.125)^5)))+((('DCF'!F14*(1+0.035))/(0.125-0.035))/((1+0.125)^5)))+'Balance Sheet'!D7) -> 551685.41 | D34: =(((('DCF'!B14/((1+0.125)^1))+('DCF'!C14/((1+0.125)^2))+('DCF'!D14/((1+0.125)^3))+('DCF'!E14/((1+0.125)^4))+('DCF'!F14/((1+0.125)^5)))+((('DCF'!F14*(1+0.04))/(0.125-0.04))/((1+0.125)^5)))+'Balance Sheet'!D7) -> 574047.51 | E34: =(((('DCF'!B14/((1+0.125)^1))+('DCF'!C14/((1+0.125)^2))+('DCF'!D14/((1+0.125)^3))+('DCF'!E14/((1+0.125)^4))+('DCF'!F14/((1+0.125)^5)))+((('DCF'!F14*(1+0.045))/(0.125-0.045))/((1+0.125)^5)))+'Balance Sheet'!D7) -> 599204.88 | F34: =(((('DCF'!B14/((1+0.125)^1))+('DCF'!C14/((1+0.125)^2))+('DCF'!D14/((1+0.125)^3))+('DCF'!E14/((1+0.125)^4))+('DCF'!F14/((1+0.125)^5)))+((('DCF'!F14*(1+0.05))/(0.125-0.05))/((1+0.125)^5)))+'Balance Sheet'!D7) -> 627716.56

Sheet Checks
A1: Checks
A3: Overall status | B3: =IF(COUNTIF(C5:C28,"CHECK")=0,"ALL OK","CHECK FAILURES") -> ALL OK
A4: Check | B4: Difference | C4: Status
A5: Balance sheet balances, FY2023 | B5: =('Balance Sheet'!B12)-('Balance Sheet'!B22) -> 0 | C5: =IF(ABS(B5)<0.5,"OK","CHECK") -> OK
A6: Balance sheet balances, FY2024 | B6: =('Balance Sheet'!C12)-('Balance Sheet'!C22) -> 1.4551915e-11 | C6: =IF(ABS(B6)<0.5,"OK","CHECK") -> OK
A7: Balance sheet balances, FY2025 | B7: =('Balance Sheet'!D12)-('Balance Sheet'!D22) -> 2.910383e-11 | C7: =IF(ABS(B7)<0.5,"OK","CHECK") -> OK
A8: Cash flow ending cash = balance sheet cash, FY2023 | B8: =('Cash Flow'!B19)-('Balance Sheet'!B7) -> 0 | C8: =IF(ABS(B8)<0.5,"OK","CHECK") -> OK
A9: Cash flow ending cash = balance sheet cash, FY2024 | B9: =('Cash Flow'!C19)-('Balance Sheet'!C7) -> 0 | C9: =IF(ABS(B9)<0.5,"OK","CHECK") -> OK
A10: Cash flow ending cash = balance sheet cash, FY2025 | B10: =('Cash Flow'!D19)-('Balance Sheet'!D7) -> 0 | C10: =IF(ABS(B10)<0.5,"OK","CHECK") -> OK
A11: Net income ties, income statement to cash flow, FY2023 | B11: =('Income Statement'!B20)-('Cash Flow'!B6) -> 0 | C11: =IF(ABS(B11)<0.5,"OK","CHECK") -> OK
A12: Net income ties, income statement to cash flow, FY2024 | B12: =('Income Statement'!C20)-('Cash Flow'!C6) -> 0 | C12: =IF(ABS(B12)<0.5,"OK","CHECK") -> OK
A13: Net income ties, income statement to cash flow, FY2025 | B13: =('Income Statement'!D20)-('Cash Flow'!D6) -> 0 | C13: =IF(ABS(B13)<0.5,"OK","CHECK") -> OK
A14: Beginning cash equals prior year ending cash, FY2023 | B14: =('Cash Flow'!B18)-('Assumptions'!B30) -> 0 | C14: =IF(ABS(B14)<0.5,"OK","CHECK") -> OK
A15: Beginning cash equals prior year ending cash, FY2024 | B15: =('Cash Flow'!C18)-('Cash Flow'!B19) -> 0 | C15: =IF(ABS(B15)<0.5,"OK","CHECK") -> OK
A16: Beginning cash equals prior year ending cash, FY2025 | B16: =('Cash Flow'!D18)-('Cash Flow'!C19) -> 0 | C16: =IF(ABS(B16)<0.5,"OK","CHECK") -> OK
A17: Accumulated deficit rolls forward, FY2023 | B17: =('Balance Sheet'!B20)-(('Assumptions'!B38+'Income Statement'!B20)) -> 0 | C17: =IF(ABS(B17)<0.5,"OK","CHECK") -> OK
A18: Accumulated deficit rolls forward, FY2024 | B18: =('Balance Sheet'!C20)-(('Balance Sheet'!B20+'Income Statement'!C20)) -> 0 | C18: =IF(ABS(B18)<0.5,"OK","CHECK") -> OK
A19: Accumulated deficit rolls forward, FY2025 | B19: =('Balance Sheet'!D20)-(('Balance Sheet'!C20+'Income Statement'!D20)) -> 0 | C19: =IF(ABS(B19)<0.5,"OK","CHECK") -> OK
A20: Total revenue equals its components, FY2023 | B20: =('Income Statement'!B8)-(('Income Statement'!B6+'Income Statement'!B7)) -> 0 | C20: =IF(ABS(B20)<0.5,"OK","CHECK") -> OK
A21: Total revenue equals its components, FY2024 | B21: =('Income Statement'!C8)-(('Income Statement'!C6+'Income Statement'!C7)) -> 0 | C21: =IF(ABS(B21)<0.5,"OK","CHECK") -> OK
A22: Total revenue equals its components, FY2025 | B22: =('Income Statement'!D8)-(('Income Statement'!D6+'Income Statement'!D7)) -> 0 | C22: =IF(ABS(B22)<0.5,"OK","CHECK") -> OK
A23: Total current assets equal their components, FY2023 | B23: =('Balance Sheet'!B10)-(('Balance Sheet'!B7+'Balance Sheet'!B8+'Balance Sheet'!B9)) -> 0 | C23: =IF(ABS(B23)<0.5,"OK","CHECK") -> OK
A24: Total current assets equal their components, FY2024 | B24: =('Balance Sheet'!C10)-(('Balance Sheet'!C7+'Balance Sheet'!C8+'Balance Sheet'!C9)) -> 0 | C24: =IF(ABS(B24)<0.5,"OK","CHECK") -> OK
A25: Total current assets equal their components, FY2025 | B25: =('Balance Sheet'!D10)-(('Balance Sheet'!D7+'Balance Sheet'!D8+'Balance Sheet'!D9)) -> 0 | C25: =IF(ABS(B25)<0.5,"OK","CHECK") -> OK
A26: Total liabilities equal their components, FY2023 | B26: =('Balance Sheet'!B17)-(('Balance Sheet'!B14+'Balance Sheet'!B15+'Balance Sheet'!B16)) -> 0 | C26: =IF(ABS(B26)<0.5,"OK","CHECK") -> OK
A27: Total liabilities equal their components, FY2024 | B27: =('Balance Sheet'!C17)-(('Balance Sheet'!C14+'Balance Sheet'!C15+'Balance Sheet'!C16)) -> 0 | C27: =IF(ABS(B27)<0.5,"OK","CHECK") -> OK
A28: Total liabilities equal their components, FY2025 | B28: =('Balance Sheet'!D17)-(('Balance Sheet'!D14+'Balance Sheet'!D15+'Balance Sheet'!D16)) -> 0 | C28: =IF(ABS(B28)<0.5,"OK","CHECK") -> OK
