Workbook

Sheet Cover
A2: Sunfield Kitchen Group
A4: Fast casual kitchens across Southern California
A6: Fiscal years covered: FY2023, FY2024, FY2025
A8: Industry: Restaurants (fast casual)
A9: Role fit: FP&A, Business analysis, Operations finance
A11: Fictional company. All figures are illustrative and were built for this portfolio.
A12: Prepared by George Murad
A14: Contents
A15: Cover
A16: Assumptions
A17: Income Statement
A18: Balance Sheet
... A29: Formula, pulls from another sheet

Sheet Assumptions
A1: Sunfield Kitchen Group
A2: Assumptions
A3: ($ in thousands)
B5: FY2023 | C5: FY2024 | D5: FY2025
A6: Restaurants open, start of FY2023 | B6: 18
A7: Restaurant openings | B7: 3 | C7: 4 | D7: 5
A8: Average unit volume (full year sales per restaurant) | B8: 2350 | C8: 2420 | D8: 2480
A9: New restaurant opening year sales factor | B9: 0.425
A10: Same restaurant sales growth | B10: 0.031 | C10: 0.029 | D10: 0.024
A11: Food and packaging, % of sales | B11: 0.295 | C11: 0.304 | D11: 0.298
A12: Labor and benefits, % of sales | B12: 0.312 | C12: 0.326 | D12: 0.329
A13: Occupancy, % of sales | B13: 0.089 | C13: 0.087 | D13: 0.085
A14: Other operating, % of sales | B14: 0.104 | C14: 0.106 | D14: 0.102
A15: General and administrative, % of sales | B15: 0.098 | C15: 0.094 | D15: 0.088
A16: Preopening cost per opening | B16: 150
A17: Depreciation and amortization, % of sales | B17: 0.043
A18: Capital expenditures per opening | B18: 1250
A19: Maintenance capital expenditures, % of sales | B19: 0.013
A20: Term loan, opening balance | B20: 12000
A21: Term loan, annual repayment | B21: 1000
A22: Term loan interest rate | B22: 0.07
A23: Revolver capacity | B23: 6000
A24: Revolver interest rate | B24: 0.08
A25: Minimum cash | B25: 2500
A26: Income tax rate | B26: 0.26
A27: Right of use asset per restaurant open at year end | B27: 1900
... A48: Opening balance sheet FY2022: Accumulated deficit | B48: -3996

Sheet Income Statement
A1: Sunfield Kitchen Group
A2: Income Statement
A3: ($ in thousands) For the years ended December 31
B5: FY2023 | C5: FY2024 | D5: FY2025
A6: Restaurant sales | B6: =(('Assumptions'!B6*'Assumptions'!B8)+(('Assumptions'!B7*'Assumptions'!B8)*'Assumptions'!B9)) -> 45296.25 | C6: =((('Assumptions'!B6+'Assumptions'!B7)*'Assumptions'!C8)+(('Assumptions'!C7*'Assumptions'!C8)*'Assumptions'!B9)) -> 54934 | D6: =(((('Assumptions'!B6+'Assumptions'!B7)+'Assumptions'!C7)*'Assumptions'!D8)+(('Assumptions'!D7*'Assumptions'!D8)*'Assumptions'!B9)) -> 67270
A7: Food and packaging | B7: =(B6*'Assumptions'!B11) -> 13362.394 | C7: =(C6*'Assumptions'!C11) -> 16699.936 | D7: =(D6*'Assumptions'!D11) -> 20046.46
A8: Labor and benefits | B8: =(B6*'Assumptions'!B12) -> 14132.43 | C8: =(C6*'Assumptions'!C12) -> 17908.484 | D8: =(D6*'Assumptions'!D12) -> 22131.83
A9: Occupancy | B9: =(B6*'Assumptions'!B13) -> 4031.3662 | C9: =(C6*'Assumptions'!C13) -> 4779.258 | D9: =(D6*'Assumptions'!D13) -> 5717.95
A10: Other operating | B10: =(B6*'Assumptions'!B14) -> 4710.81 | C10: =(C6*'Assumptions'!C14) -> 5823.004 | D10: =(D6*'Assumptions'!D14) -> 6861.54
A11: Restaurant level profit | B11: =((((B6-B7)-B8)-B9)-B10) -> 9059.25 | C11: =((((C6-C7)-C8)-C9)-C10) -> 9723.318 | D11: =((((D6-D7)-D8)-D9)-D10) -> 12512.22
A12: General and administrative | B12: =(B6*'Assumptions'!B15) -> 4439.0325 | C12: =(C6*'Assumptions'!C15) -> 5163.796 | D12: =(D6*'Assumptions'!D15) -> 5919.76
A13: Preopening costs | B13: =('Assumptions'!B7*'Assumptions'!B16) -> 450 | C13: =('Assumptions'!C7*'Assumptions'!B16) -> 600 | D13: =('Assumptions'!D7*'Assumptions'!B16) -> 750
A14: EBITDA | B14: =((B11-B12)-B13) -> 4170.2175 | C14: =((C11-C12)-C13) -> 3959.522 | D14: =((D11-D12)-D13) -> 5842.46
A15: Depreciation and amortization | B15: =(B6*'Assumptions'!B17) -> 1947.7387 | C15: =(C6*'Assumptions'!B17) -> 2362.162 | D15: =(D6*'Assumptions'!B17) -> 2892.61
A16: Operating income | B16: =(B14-B15) -> 2222.4788 | C16: =(C14-C15) -> 1597.36 | D16: =(D14-D15) -> 2949.85
A17: Interest expense | B17: =(('Assumptions'!B46*'Assumptions'!B22)+('Assumptions'!B45*'Assumptions'!B24)) -> 840 | C17: =(('Balance Sheet'!B22*'Assumptions'!B22)+('Balance Sheet'!B21*'Assumptions'!B24)) -> 839.23616 | D17: =(('Balance Sheet'!C22*'Assumptions'!B22)+('Balance Sheet'!C21*'Assumptions'!B24)) -> 967.58917
A18: Income before taxes | B18: =(B16-B17) -> 1382.4788 | C18: =(C16-C17) -> 758.12384 | D18: =(D16-D17) -> 1982.2608
A19: Income tax expense | B19: =MAX(0,(B18*'Assumptions'!B26)) -> 359.44448 | C19: =MAX(0,(C18*'Assumptions'!B26)) -> 197.1122 | D19: =MAX(0,(D18*'Assumptions'!B26)) -> 515.38782
A20: Net income | B20: =(B18-B19) -> 1023.0343 | C20: =(C18-C19) -> 561.01164 | D20: =(D18-D19) -> 1466.873
A21: Restaurant level margin | B21: =(B11/B6) -> 0.2 | C21: =(C11/C6) -> 0.177 | D21: =(D11/D6) -> 0.186
A22: EBITDA margin | B22: =(B14/B6) -> 0.092065403 | C22: =(C14/C6) -> 0.072077802 | D22: =(D14/D6) -> 0.086850899
A23: Restaurants at year end | B23: =('Assumptions'!B6+'Assumptions'!B7) -> 21 | C23: =(('Assumptions'!B6+'Assumptions'!B7)+'Assumptions'!C7) -> 25 | D23: =((('Assumptions'!B6+'Assumptions'!B7)+'Assumptions'!C7)+'Assumptions'!D7) -> 30
A24: Same restaurant sales growth | B24: ='Assumptions'!B10 -> 0.031 | C24: ='Assumptions'!C10 -> 0.029 | D24: ='Assumptions'!D10 -> 0.024

Sheet Balance Sheet
A1: Sunfield Kitchen Group
A2: Balance Sheet
A3: ($ in thousands) As of December 31
B5: FY2023 | C5: FY2024 | D5: FY2025
A6: Assets
A7: Cash and cash equivalents | B7: ='Cash Flow'!B23 -> 2500 | C7: ='Cash Flow'!C23 -> 2500 | D7: ='Cash Flow'!D23 -> 2500
A8: Receivables | B8: =('Income Statement'!B6*'Assumptions'!B30) -> 543.555 | C8: =('Income Statement'!C6*'Assumptions'!B30) -> 659.208 | D8: =('Income Statement'!D6*'Assumptions'!B30) -> 807.24
A9: Inventory | B9: =('Income Statement'!B6*'Assumptions'!B29) -> 362.37 | C9: =('Income Statement'!C6*'Assumptions'!B29) -> 439.472 | D9: =('Income Statement'!D6*'Assumptions'!B29) -> 538.16
A10: Prepaid expenses | B10: =('Income Statement'!B6*'Assumptions'!B31) -> 407.66625 | C10: =('Income Statement'!C6*'Assumptions'!B31) -> 494.406 | D10: =('Income Statement'!D6*'Assumptions'!B31) -> 605.43
A11: Total current assets | B11: =(B7+B8+B9+B10) -> 3813.5912 | C11: =(C7+C8+C9+C10) -> 4093.086 | D11: =(D7+D8+D9+D10) -> 4450.83
A12: Property, plant and equipment, net | B12: =(('Assumptions'!B39+(('Assumptions'!B7*'Assumptions'!B18)+('Income Statement'!B6*'Assumptions'!B19)))-'Income Statement'!B15) -> 21891.112 | C12: =((B12+(('Assumptions'!C7*'Assumptions'!B18)+('Income Statement'!C6*'Assumptions'!B19)))-'Income Statement'!C15) -> 25243.092 | D12: =((C12+(('Assumptions'!D7*'Assumptions'!B18)+('Income Statement'!D6*'Assumptions'!B19)))-'Income Statement'!D15) -> 29474.993
A13: Right of use assets | B13: =('Income Statement'!B23*'Assumptions'!B27) -> 39900 | C13: =('Income Statement'!C23*'Assumptions'!B27) -> 47500 | D13: =('Income Statement'!D23*'Assumptions'!B27) -> 57000
A14: Total assets | B14: =((B11+B12)+B13) -> 65604.704 | C14: =((C11+C12)+C13) -> 76836.178 | D14: =((D11+D12)+D13) -> 90925.823
A15: Liabilities
A16: Accounts payable | B16: =('Income Statement'!B6*'Assumptions'!B32) -> 1902.4425 | C16: =('Income Statement'!C6*'Assumptions'!B32) -> 2307.228 | D16: =('Income Statement'!D6*'Assumptions'!B32) -> 2825.34
A17: Accrued wages and taxes | B17: =('Income Statement'!B6*'Assumptions'!B33) -> 2264.8125 | C17: =('Income Statement'!C6*'Assumptions'!B33) -> 2746.7 | D17: =('Income Statement'!D6*'Assumptions'!B33) -> 3363.5
A18: Gift card liability | B18: =('Income Statement'!B6*'Assumptions'!B34) -> 452.9625 | C18: =('Income Statement'!C6*'Assumptions'!B34) -> 549.34 | D18: =('Income Statement'!D6*'Assumptions'!B34) -> 672.7
A19: Total current liabilities | B19: =(B16+B17+B18) -> 4620.2175 | C19: =(C16+C17+C18) -> 5603.268 | D19: =(D16+D17+D18) -> 6861.54
A20: Operating lease liabilities | B20: =(B13*'Assumptions'!B28) -> 43092 | C20: =(C13*'Assumptions'!B28) -> 51300 | D20: =(D13*'Assumptions'!B28) -> 61560
A21: Revolver | B21: =(('Assumptions'!B45+MAX(0,MIN(('Assumptions'!B25-((('Assumptions'!B35+'Cash Flow'!B15)+'Cash Flow'!B17)+'Cash Flow'!B18)),('Assumptions'!B23-'Assumptions'!B45))))-MAX(0,MIN('Assumptions'!B45,(((('Assumptions'!B35+'Cash Flow'!B15)+'Cash Flow'!B17)+'Cash Flow'!B18)-'Assumptions'!B25)))) -> 865.45197 | C21: =(('Balance Sheet'!B21+MAX(0,MIN(('Assumptions'!B25-((('Balance Sheet'!B7+'Cash Flow'!C15)+'Cash Flow'!C17)+'Cash Flow'!C18)),('Assumptions'!B23-'Balance Sheet'!B21))))-MAX(0,MIN('Balance Sheet'!B21,(((('Balance Sheet'!B7+'Cash Flow'!C15)+'Cash Flow'!C17)+'Cash Flow'!C18)-'Assumptions'!B25)))) -> 3344.8646 | D21: =(('Balance Sheet'!C21+MAX(0,MIN(('Assumptions'!B25-((('Balance Sheet'!C7+'Cash Flow'!D15)+'Cash Flow'!D17)+'Cash Flow'!D18)),('Assumptions'!B23-'Balance Sheet'!C21))))-MAX(0,MIN('Balance Sheet'!C21,(((('Balance Sheet'!C7+'Cash Flow'!D15)+'Cash Flow'!D17)+'Cash Flow'!D18)-'Assumptions'!B25)))) -> 5449.3636
A22: Term loan | B22: =('Assumptions'!B46-'Assumptions'!B21) -> 11000 | C22: =('Balance Sheet'!B22-'Assumptions'!B21) -> 10000 | D22: =('Balance Sheet'!C22-'Assumptions'!B21) -> 9000
A23: Total liabilities | B23: =(((B19+B20)+B21)+B22) -> 59577.669 | C23: =(((C19+C20)+C21)+C22) -> 70248.133 | D23: =(((D19+D20)+D21)+D22) -> 82870.904
A24: Equity
A25: Common stock and paid in capital | B25: ='Assumptions'!B47 -> 9000 | C25: ='Assumptions'!B47 -> 9000 | D25: ='Assumptions'!B47 -> 9000
A26: Accumulated deficit | B26: =('Assumptions'!B48+'Income Statement'!B20) -> -2972.9657 | C26: =(B26+'Income Statement'!C20) -> -2411.9541 | D26: =(C26+'Income Statement'!D20) -> -945.08107
A27: Total equity | B27: =(B25+B26) -> 6027.0343 | C27: =(C25+C26) -> 6588.0459 | D27: =(D25+D26) -> 8054.9189
A28: Total liabilities and equity | B28: =(B23+B27) -> 65604.704 | C28: =(C23+C27) -> 76836.178 | D28: =(D23+D27) -> 90925.822

Sheet Cash Flow
A1: Sunfield Kitchen Group
A2: Cash Flow Statement
A3: ($ in thousands) For the years ended December 31
B5: FY2023 | C5: FY2024 | D5: FY2025
A6: Net income | B6: ='Income Statement'!B20 -> 1023.0343 | C6: ='Income Statement'!C20 -> 561.01164 | D6: ='Income Statement'!D20 -> 1466.873
A7: Depreciation and amortization | B7: ='Income Statement'!B15 -> 1947.7387 | C7: ='Income Statement'!C15 -> 2362.162 | D7: ='Income Statement'!D15 -> 2892.61
A8: Noncash lease adjustment | B8: =(('Balance Sheet'!B20-'Assumptions'!B44)-('Balance Sheet'!B13-'Assumptions'!B40)) -> 456 | C8: =(('Balance Sheet'!C20-'Balance Sheet'!B20)-('Balance Sheet'!C13-'Balance Sheet'!B13)) -> 608 | D8: =(('Balance Sheet'!D20-'Balance Sheet'!C20)-('Balance Sheet'!D13-'Balance Sheet'!C13)) -> 760
A9: (Increase) decrease in receivables | B9: =(-('Balance Sheet'!B8-'Assumptions'!B36)) -> -83.555 | C9: =(-('Balance Sheet'!C8-'Balance Sheet'!B8)) -> -115.653 | D9: =(-('Balance Sheet'!D8-'Balance Sheet'!C8)) -> -148.032
A10: (Increase) decrease in inventory | B10: =(-('Balance Sheet'!B9-'Assumptions'!B37)) -> -52.37 | C10: =(-('Balance Sheet'!C9-'Balance Sheet'!B9)) -> -77.102 | D10: =(-('Balance Sheet'!D9-'Balance Sheet'!C9)) -> -98.688
A11: (Increase) decrease in prepaid expenses | B11: =(-('Balance Sheet'!B10-'Assumptions'!B38)) -> -57.66625 | C11: =(-('Balance Sheet'!C10-'Balance Sheet'!B10)) -> -86.73975 | D11: =(-('Balance Sheet'!D10-'Balance Sheet'!C10)) -> -111.024
A12: Increase (decrease) in accounts payable | B12: =('Balance Sheet'!B16-'Assumptions'!B41) -> 262.4425 | C12: =('Balance Sheet'!C16-'Balance Sheet'!B16) -> 404.7855 | D12: =('Balance Sheet'!D16-'Balance Sheet'!C16) -> 518.112
A13: Increase (decrease) in accrued wages and taxes | B13: =('Balance Sheet'!B17-'Assumptions'!B42) -> 314.8125 | C13: =('Balance Sheet'!C17-'Balance Sheet'!B17) -> 481.8875 | D13: =('Balance Sheet'!D17-'Balance Sheet'!C17) -> 616.8
A14: Increase (decrease) in gift card liability | B14: =('Balance Sheet'!B18-'Assumptions'!B43) -> 62.9625 | C14: =('Balance Sheet'!C18-'Balance Sheet'!B18) -> 96.3775 | D14: =('Balance Sheet'!D18-'Balance Sheet'!C18) -> 123.36
A15: Cash from operating activities | B15: =(B6+B7+B8+B9+B10+B11+B12+B13+B14) -> 3873.3993 | C15: =(C6+C7+C8+C9+C10+C11+C12+C13+C14) -> 4234.7294 | D15: =(D6+D7+D8+D9+D10+D11+D12+D13+D14) -> 6020.011
A16: Capital expenditures | B16: =(-(('Assumptions'!B7*'Assumptions'!B18)+('Income Statement'!B6*'Assumptions'!B19))) -> -4338.8512 | C16: =(-(('Assumptions'!C7*'Assumptions'!B18)+('Income Statement'!C6*'Assumptions'!B19))) -> -5714.142 | D16: =(-(('Assumptions'!D7*'Assumptions'!B18)+('Income Statement'!D6*'Assumptions'!B19))) -> -7124.51
A17: Cash from investing activities | B17: =B16 -> -4338.8512 | C17: =C16 -> -5714.142 | D17: =D16 -> -7124.51
A18: Term loan repayment | B18: =(-'Assumptions'!B21) -> -1000 | C18: =(-'Assumptions'!B21) -> -1000 | D18: =(-'Assumptions'!B21) -> -1000
A19: Revolver draw (repayment) | B19: =(MAX(0,MIN(('Assumptions'!B25-((('Assumptions'!B35+B15)+B17)+B18)),('Assumptions'!B23-'Assumptions'!B45)))-MAX(0,MIN('Assumptions'!B45,(((('Assumptions'!B35+B15)+B17)+B18)-'Assumptions'!B25)))) -> 865.45197 | C19: =(MAX(0,MIN(('Assumptions'!B25-((('Balance Sheet'!B7+C15)+C17)+C18)),('Assumptions'!B23-'Balance Sheet'!B21)))-MAX(0,MIN('Balance Sheet'!B21,(((('Balance Sheet'!B7+C15)+C17)+C18)-'Assumptions'!B25)))) -> 2479.4126 | D19: =(MAX(0,MIN(('Assumptions'!B25-((('Balance Sheet'!C7+D15)+D17)+D18)),('Assumptions'!B23-'Balance Sheet'!C21)))-MAX(0,MIN('Balance Sheet'!C21,(((('Balance Sheet'!C7+D15)+D17)+D18)-'Assumptions'!B25)))) -> 2104.499
A20: Cash from financing activities | B20: =(B18+B19) -> -134.54803 | C20: =(C18+C19) -> 1479.4126 | D20: =(D18+D19) -> 1104.499
A21: Net change in cash | B21: =((B15+B17)+B20) -> -600 | C21: =((C15+C17)+C20) -> 9.094947e-13 | D21: =((D15+D17)+D20) -> -9.094947e-13
A22: Beginning cash | B22: ='Assumptions'!B35 -> 3100 | C22: ='Balance Sheet'!B7 -> 2500 | D22: ='Balance Sheet'!C7 -> 2500
A23: Ending cash | B23: =(B22+B21) -> 2500 | C23: =(C22+C21) -> 2500 | D23: =(D22+D21) -> 2500
B26: FY2023 | C26: FY2024 | D26: FY2025
A27: Cash before revolver | B27: =((('Assumptions'!B35+B15)+B17)+B18) -> 1634.548 | C27: =((('Balance Sheet'!B7+C15)+C17)+C18) -> 20.587393 | D27: =((('Balance Sheet'!C7+D15)+D17)+D18) -> 395.50102

Sheet Ratios
A1: Sunfield Kitchen Group
A2: Ratios
A3: ($ in thousands)
B5: FY2023 | C5: FY2024 | D5: FY2025
A6: Restaurant level margin | B6: =('Income Statement'!B11/'Income Statement'!B6) -> 0.2 | C6: =('Income Statement'!C11/'Income Statement'!C6) -> 0.177 | D6: =('Income Statement'!D11/'Income Statement'!D6) -> 0.186
A7: EBITDA margin | B7: =('Income Statement'!B14/'Income Statement'!B6) -> 0.092065403 | C7: =('Income Statement'!C14/'Income Statement'!C6) -> 0.072077802 | D7: =('Income Statement'!D14/'Income Statement'!D6) -> 0.086850899
A8: Operating margin | B8: =('Income Statement'!B16/'Income Statement'!B6) -> 0.049065403 | C8: =('Income Statement'!C16/'Income Statement'!C6) -> 0.029077802 | D8: =('Income Statement'!D16/'Income Statement'!D6) -> 0.043850899
A9: Net margin | B9: =('Income Statement'!B20/'Income Statement'!B6) -> 0.022585408 | C9: =('Income Statement'!C20/'Income Statement'!C6) -> 0.010212467 | D9: =('Income Statement'!D20/'Income Statement'!D6) -> 0.021805753
A10: Revenue growth | B10: n/a | C10: =(('Income Statement'!C6/'Income Statement'!B6)-1) -> 0.21277148 | D10: =(('Income Statement'!D6/'Income Statement'!C6)-1) -> 0.22456038
A11: Current ratio | B11: =('Balance Sheet'!B11/'Balance Sheet'!B19) -> 0.82541379 | C11: =('Balance Sheet'!C11/'Balance Sheet'!C19) -> 0.73048193 | D11: =('Balance Sheet'!D11/'Balance Sheet'!D19) -> 0.64866342
A12: Debt to EBITDA, excluding leases | B12: =(('Balance Sheet'!B21+'Balance Sheet'!B22)/'Income Statement'!B14) -> 2.8452837 | C12: =(('Balance Sheet'!C21+'Balance Sheet'!C22)/'Income Statement'!C14) -> 3.3703221 | D12: =(('Balance Sheet'!D21+'Balance Sheet'!D22)/'Income Statement'!D14) -> 2.4731643
A13: Return on equity | B13: =('Income Statement'!B20/((('Assumptions'!B47+'Assumptions'!B48)+'Balance Sheet'!B27)/2)) -> 0.18548293 | C13: =('Income Statement'!C20/(('Balance Sheet'!B27+'Balance Sheet'!C27)/2)) -> 0.088943017 | D13: =('Income Statement'!D20/(('Balance Sheet'!C27+'Balance Sheet'!D27)/2)) -> 0.20035191
A14: Days inventory outstanding | B14: =(('Balance Sheet'!B9/'Income Statement'!B7)*365) -> 9.8983051 | C14: =(('Balance Sheet'!C9/'Income Statement'!C7)*365) -> 9.6052632 | D14: =(('Balance Sheet'!D9/'Income Statement'!D7)*365) -> 9.7986577
A15: Days payable, food and packaging | B15: =(('Balance Sheet'!B16/'Income Statement'!B7)*365) -> 51.966102 | C15: =(('Balance Sheet'!C16/'Income Statement'!C7)*365) -> 50.427632 | D15: =(('Balance Sheet'!D16/'Income Statement'!D7)*365) -> 51.442953
A16: Free cash flow | B16: =('Cash Flow'!B15+'Cash Flow'!B16) -> -465.45197 | C16: =('Cash Flow'!C15+'Cash Flow'!C16) -> -1479.4126 | D16: =('Cash Flow'!D15+'Cash Flow'!D16) -> -1104.499
A17: FCF margin | B17: =(('Cash Flow'!B15+'Cash Flow'!B16)/'Income Statement'!B6) -> -0.010275729 | C17: =(('Cash Flow'!C15+'Cash Flow'!C16)/'Income Statement'!C6) -> -0.026930728 | D17: =(('Cash Flow'!D15+'Cash Flow'!D16)/'Income Statement'!D6) -> -0.016418894

Sheet Unit Economics
A1: Sunfield Kitchen Group
A2: New restaurant economics
A3: ($ in thousands)
B5: Value
A6: Build cost per restaurant | B6: ='Assumptions'!B18 -> 1250
A7: Preopening cost per restaurant | B7: ='Assumptions'!B16 -> 150
A8: Total investment per restaurant | B8: =(B6+B7) -> 1400
A9: Mature sales (FY2025 AUV) | B9: ='Assumptions'!D8 -> 2480
A10: Restaurant level margin (FY2025) | B10: ='Income Statement'!D21 -> 0.186
A11: Restaurant level profit per restaurant | B11: =(B9*B10) -> 461.28
A12: Cash on cash return | B12: =(B11/B8) -> 0.32948571
A13: Payback, years | B13: =(B8/B11) -> 3.035033

Sheet Cohorts
A1: Sunfield Kitchen Group
A2: FY2025 restaurants by opening class
A3: ($ in thousands)
B5: Restaurants | C5: Sales | D5: Sales per restaurant | E5: Restaurant level margin | F5: Restaurant level profit
A6: Legacy (opened before FY2023) | B6: =18 -> 18 | C6: =45180 -> 45180 | D6: =(45180/18) -> 2510 | E6: =0.196 -> 0.196 | F6: =(45180*0.196) -> 8855.28
A7: Class of 2023 | B7: =3 -> 3 | C7: =7410 -> 7410 | D7: =(7410/3) -> 2470 | E7: =0.184 -> 0.184 | F7: =(7410*0.184) -> 1363.44
A8: Class of 2024 | B8: =4 -> 4 | C8: =9520 -> 9520 | D8: =(9520/4) -> 2380 | E8: =0.171 -> 0.171 | F8: =(9520*0.171) -> 1627.92
A9: Class of 2025 | B9: =5 -> 5 | C9: =5160 -> 5160 | D9: =(5160/5) -> 1032 | E9: =0.129 -> 0.129 | F9: =(5160*0.129) -> 665.64
A10: Total | B10: =(18+3+4+5) -> 30 | C10: =(45180+7410+9520+5160) -> 67270 | D10: =((45180+7410+9520+5160)/(18+3+4+5)) -> 2242.3333 | E10: =(((45180*0.196)+(7410*0.184)+(9520*0.171)+(5160*0.129))/(45180+7410+9520+5160)) -> 0.18600089 | F10: =((45180*0.196)+(7410*0.184)+(9520*0.171)+(5160*0.129)) -> 12512.28
A11: Check: total sales vs FY2025 revenue | B11: n/a | C11: =((45180+7410+9520+5160)-'Income Statement'!D6) -> 0 | D11: n/a | E11: n/a | F11: n/a
A12: Check: total profit vs FY2025 restaurant level profit | B12: n/a | C12: n/a | D12: n/a | E12: n/a | F12: =(((45180*0.196)+(7410*0.184)+(9520*0.171)+(5160*0.129))-'Income Statement'!D11) -> 0.06

Sheet Budget vs Actual
A1: Sunfield Kitchen Group
A2: FY2025 budget versus actual, full year
A3: ($ in thousands)
B5: Budget | C5: Actual | D5: Variance | E5: Variance % | F5: Status
A6: Restaurant sales | B6: =68900 -> 68900 | C6: ='Income Statement'!D6 -> 67270 | D6: =(C6-B6) -> -1630 | E6: =(D6/B6) -> -0.023657475 | F6: Unfavorable
A7: Food and packaging | B7: =(68900*0.295) -> 20325.5 | C7: ='Income Statement'!D7 -> 20046.46 | D7: =(B7-C7) -> 279.04 | E7: =(D7/B7) -> 0.013728568 | F7: Favorable
A8: Labor and benefits | B8: =(68900*0.324) -> 22323.6 | C8: ='Income Statement'!D8 -> 22131.83 | D8: =(B8-C8) -> 191.77 | E8: =(D8/B8) -> 0.0085904603 | F8: Favorable
A9: Occupancy | B9: =(68900*0.084) -> 5787.6 | C9: ='Income Statement'!D9 -> 5717.95 | D9: =(B9-C9) -> 69.65 | E9: =(D9/B9) -> 0.012034349 | F9: Favorable
A10: Other operating | B10: =(68900*0.1) -> 6890 | C10: ='Income Statement'!D10 -> 6861.54 | D10: =(B10-C10) -> 28.46 | E10: =(D10/B10) -> 0.0041306241 | F10: Favorable
A11: Restaurant level profit | B11: =(B6-((68900*0.295)+(68900*0.324)+(68900*0.084)+(68900*0.1))) -> 13573.3 | C11: ='Income Statement'!D11 -> 12512.22 | D11: =(C11-B11) -> -1061.08 | E11: =(D11/B11) -> -0.078174062 | F11: Unfavorable
B14: Q1 | C14: Q2 | D14: Q3 | E14: Q4 | F14: Total
A15: Budget sales | B15: =16200 -> 16200 | C15: =17400 -> 17400 | D15: =17900 -> 17900 | E15: =17400 -> 17400 | F15: =(B15+C15+D15+E15) -> 68900
A16: Actual sales | B16: =15950 -> 15950 | C16: =16980 -> 16980 | D16: =17520 -> 17520 | E16: =16820 -> 16820 | F16: =(B16+C16+D16+E16) -> 67270
A17: Variance | B17: =(B16-B15) -> -250 | C17: =(C16-C15) -> -420 | D17: =(D16-D15) -> -380 | E17: =(E16-E15) -> -580 | F17: =(F16-F15) -> -1630

Sheet Checks
A1: Checks
A3: Overall status | B3: =IF(COUNTIF(C5:C25,"CHECK")=0,"ALL OK","CHECK FAILURES") -> ALL OK
A4: Check | B4: Difference | C4: Status
A5: Balance sheet balances, FY2023 | B5: =('Balance Sheet'!B14)-('Balance Sheet'!B28) -> 0 | C5: =IF(ABS(B5)<0.5,"OK","CHECK") -> OK
A6: Balance sheet balances, FY2024 | B6: =('Balance Sheet'!C14)-('Balance Sheet'!C28) -> 0 | C6: =IF(ABS(B6)<0.5,"OK","CHECK") -> OK
A7: Balance sheet balances, FY2025 | B7: =('Balance Sheet'!D14)-('Balance Sheet'!D28) -> 1.4551915e-11 | C7: =IF(ABS(B7)<0.5,"OK","CHECK") -> OK
A8: Cash flow ending cash = balance sheet cash, FY2023 | B8: =('Cash Flow'!B23)-('Balance Sheet'!B7) -> 0 | C8: =IF(ABS(B8)<0.5,"OK","CHECK") -> OK
A9: Cash flow ending cash = balance sheet cash, FY2024 | B9: =('Cash Flow'!C23)-('Balance Sheet'!C7) -> 0 | C9: =IF(ABS(B9)<0.5,"OK","CHECK") -> OK
A10: Cash flow ending cash = balance sheet cash, FY2025 | B10: =('Cash Flow'!D23)-('Balance Sheet'!D7) -> 0 | C10: =IF(ABS(B10)<0.5,"OK","CHECK") -> OK
A11: Net income ties, income statement to cash flow, FY2023 | B11: =('Income Statement'!B20)-('Cash Flow'!B6) -> 0 | C11: =IF(ABS(B11)<0.5,"OK","CHECK") -> OK
A12: Net income ties, income statement to cash flow, FY2024 | B12: =('Income Statement'!C20)-('Cash Flow'!C6) -> 0 | C12: =IF(ABS(B12)<0.5,"OK","CHECK") -> OK
A13: Net income ties, income statement to cash flow, FY2025 | B13: =('Income Statement'!D20)-('Cash Flow'!D6) -> 0 | C13: =IF(ABS(B13)<0.5,"OK","CHECK") -> OK
A14: Beginning cash equals prior year ending cash, FY2023 | B14: =('Cash Flow'!B22)-('Assumptions'!B35) -> 0 | C14: =IF(ABS(B14)<0.5,"OK","CHECK") -> OK
A15: Beginning cash equals prior year ending cash, FY2024 | B15: =('Cash Flow'!C22)-('Cash Flow'!B23) -> 0 | C15: =IF(ABS(B15)<0.5,"OK","CHECK") -> OK
A16: Beginning cash equals prior year ending cash, FY2025 | B16: =('Cash Flow'!D22)-('Cash Flow'!C23) -> 0 | C16: =IF(ABS(B16)<0.5,"OK","CHECK") -> OK
A17: Accumulated deficit rolls forward, FY2023 | B17: =('Balance Sheet'!B26)-(('Assumptions'!B48+'Income Statement'!B20)) -> 0 | C17: =IF(ABS(B17)<0.5,"OK","CHECK") -> OK
A18: Accumulated deficit rolls forward, FY2024 | B18: =('Balance Sheet'!C26)-(('Balance Sheet'!B26+'Income Statement'!C20)) -> 0 | C18: =IF(ABS(B18)<0.5,"OK","CHECK") -> OK
A19: Accumulated deficit rolls forward, FY2025 | B19: =('Balance Sheet'!D26)-(('Balance Sheet'!C26+'Income Statement'!D20)) -> 0 | C19: =IF(ABS(B19)<0.5,"OK","CHECK") -> OK
A20: Total current assets equal their components, FY2023 | B20: =('Balance Sheet'!B11)-(('Balance Sheet'!B7+'Balance Sheet'!B8+'Balance Sheet'!B9+'Balance Sheet'!B10)) -> 0 | C20: =IF(ABS(B20)<0.5,"OK","CHECK") -> OK
A21: Total current assets equal their components, FY2024 | B21: =('Balance Sheet'!C11)-(('Balance Sheet'!C7+'Balance Sheet'!C8+'Balance Sheet'!C9+'Balance Sheet'!C10)) -> 0 | C21: =IF(ABS(B21)<0.5,"OK","CHECK") -> OK
A22: Total current assets equal their components, FY2025 | B22: =('Balance Sheet'!D11)-(('Balance Sheet'!D7+'Balance Sheet'!D8+'Balance Sheet'!D9+'Balance Sheet'!D10)) -> 0 | C22: =IF(ABS(B22)<0.5,"OK","CHECK") -> OK
A23: Total liabilities equal their components, FY2023 | B23: =('Balance Sheet'!B23)-(('Balance Sheet'!B19+'Balance Sheet'!B20+'Balance Sheet'!B21+'Balance Sheet'!B22)) -> 0 | C23: =IF(ABS(B23)<0.5,"OK","CHECK") -> OK
A24: Total liabilities equal their components, FY2024 | B24: =('Balance Sheet'!C23)-(('Balance Sheet'!C19+'Balance Sheet'!C20+'Balance Sheet'!C21+'Balance Sheet'!C22)) -> 0 | C24: =IF(ABS(B24)<0.5,"OK","CHECK") -> OK
A25: Total liabilities equal their components, FY2025 | B25: =('Balance Sheet'!D23)-(('Balance Sheet'!D19+'Balance Sheet'!D20+'Balance Sheet'!D21+'Balance Sheet'!D22)) -> 0 | C25: =IF(ABS(B25)<0.5,"OK","CHECK") -> OK
