Workbook

Sheet Cover
A2: Saltbrush Beverage Co.
A4: Sparkling botanical water canned in Southern California
A6: Fiscal years covered: FY2023, FY2024, FY2025
A8: Industry: Consumer products manufacturer (beverages)
A9: Role fit: Cost analysis, FP&A, Treasury
A11: Fictional company. All figures are illustrative and were built for this portfolio.
A12: Prepared by George Murad
A14: Contents
A15: Cover
A16: Assumptions
A17: Income Statement
A18: Balance Sheet
... A29: Formula, pulls from another sheet

Sheet Assumptions
A1: Saltbrush Beverage Co.
A2: Assumptions
A3: ($ in thousands, except per case amounts)
B5: FY2023 | C5: FY2024 | D5: FY2025
A6: Cases sold (thousands) | B6: 4850 | C6: 5420 | D6: 5960
A7: Net price per case | B7: 11.4 | C7: 11.85 | D7: 12.1
A8: Standard cost per case | B8: 6.95 | C8: 7.3 | D8: 7.42
A9: Manufacturing variances, FY2023 | B9: 410
A10: Manufacturing variances, FY2024 | B10: 690
A11: Selling and distribution, % of revenue | B11: 0.115 | C11: 0.118 | D11: 0.12
A12: Marketing, % of revenue | B12: 0.06 | C12: 0.065 | D12: 0.065
A13: General and administrative, % of revenue | B13: 0.075 | C13: 0.072 | D13: 0.07
A14: Depreciation, % of beginning net PP&E | B14: 0.1
A15: Capital expenditures | B15: 2600 | C15: 5800 | D15: 2200
A16: Equipment loan, opening balance | B16: 9000
A17: Equipment loan, annual repayment | B17: 1500
A18: Equipment loan interest rate | B18: 0.0675
A19: Revolver capacity | B19: 8000
A20: Revolver interest rate | B20: 0.075
A21: Minimum cash | B21: 1500
A22: Income tax rate | B22: 0.25
A23: Accounts receivable days | B23: 38
A24: Inventory days | B24: 55
A25: Prepaid expenses, % of revenue | B25: 0.01
A26: Accounts payable days | B26: 45
A27: Accrued liabilities, % of revenue | B27: 0.04
... A38: Opening balance sheet FY2022: Retained earnings | B38: 7300

Sheet Income Statement
A1: Saltbrush Beverage Co.
A2: Income Statement
A3: ($ in thousands, except per case amounts) For the years ended December 31
B5: FY2023 | C5: FY2024 | D5: FY2025
A6: Revenue | B6: =('Assumptions'!B6*'Assumptions'!B7) -> 55290 | C6: =('Assumptions'!C6*'Assumptions'!C7) -> 64227 | D6: =('Assumptions'!D6*'Assumptions'!D7) -> 72116
A7: Cost of sales at standard | B7: =('Assumptions'!B6*'Assumptions'!B8) -> 33707.5 | C7: =('Assumptions'!C6*'Assumptions'!C8) -> 39566 | D7: =('Assumptions'!D6*'Assumptions'!D8) -> 44223.2
A8: Manufacturing variances | B8: ='Assumptions'!B9 -> 410 | C8: ='Assumptions'!B10 -> 690 | D8: ='Variances'!B18 -> 2283.52
A9: Gross profit | B9: =((B6-B7)-B8) -> 21172.5 | C9: =((C6-C7)-C8) -> 23971 | D9: =((D6-D7)-D8) -> 25609.28
A10: Selling and distribution | B10: =(B6*'Assumptions'!B11) -> 6358.35 | C10: =(C6*'Assumptions'!C11) -> 7578.786 | D10: =(D6*'Assumptions'!D11) -> 8653.92
A11: Marketing | B11: =(B6*'Assumptions'!B12) -> 3317.4 | C11: =(C6*'Assumptions'!C12) -> 4174.755 | D11: =(D6*'Assumptions'!D12) -> 4687.54
A12: General and administrative | B12: =(B6*'Assumptions'!B13) -> 4146.75 | C12: =(C6*'Assumptions'!C13) -> 4624.344 | D12: =(D6*'Assumptions'!D13) -> 5048.12
A13: EBITDA | B13: =(((B9-B10)-B11)-B12) -> 7350 | C13: =(((C9-C10)-C11)-C12) -> 7593.115 | D13: =(((D9-D10)-D11)-D12) -> 7219.7
A14: Depreciation | B14: =('Assumptions'!B32*'Assumptions'!B14) -> 1480 | C14: =('Balance Sheet'!B12*'Assumptions'!B14) -> 1592 | D14: =('Balance Sheet'!C12*'Assumptions'!B14) -> 2012.8
A15: Operating income | B15: =(B13-B14) -> 5870 | C15: =(C13-C14) -> 6001.115 | D15: =(D13-D14) -> 5206.9
A16: Interest expense | B16: =(('Assumptions'!B36*'Assumptions'!B18)+('Assumptions'!B35*'Assumptions'!B20)) -> 607.5 | C16: =(('Balance Sheet'!B19*'Assumptions'!B18)+('Balance Sheet'!B18*'Assumptions'!B20)) -> 506.25 | D16: =(('Balance Sheet'!C19*'Assumptions'!B18)+('Balance Sheet'!C18*'Assumptions'!B20)) -> 414.20377
A17: Income before taxes | B17: =(B15-B16) -> 5262.5 | C17: =(C15-C16) -> 5494.865 | D17: =(D15-D16) -> 4792.6962
A18: Income tax expense | B18: =MAX(0,(B17*'Assumptions'!B22)) -> 1315.625 | C18: =MAX(0,(C17*'Assumptions'!B22)) -> 1373.7162 | D18: =MAX(0,(D17*'Assumptions'!B22)) -> 1198.1741
A19: Net income | B19: =(B17-B18) -> 3946.875 | C19: =(C17-C18) -> 4121.1487 | D19: =(D17-D18) -> 3594.5222
A20: Cases sold (thousands) | B20: ='Assumptions'!B6 -> 4850 | C20: ='Assumptions'!C6 -> 5420 | D20: ='Assumptions'!D6 -> 5960
A21: Net price per case | B21: ='Assumptions'!B7 -> 11.4 | C21: ='Assumptions'!C7 -> 11.85 | D21: ='Assumptions'!D7 -> 12.1
A22: Standard cost per case | B22: ='Assumptions'!B8 -> 6.95 | C22: ='Assumptions'!C8 -> 7.3 | D22: ='Assumptions'!D8 -> 7.42
A23: Gross margin | B23: =(B9/B6) -> 0.38293543 | C23: =(C9/C6) -> 0.3732231 | D23: =(D9/D6) -> 0.35511232

Sheet Balance Sheet
A1: Saltbrush Beverage Co.
A2: Balance Sheet
A3: ($ in thousands, except per case amounts) As of December 31
B5: FY2023 | C5: FY2024 | D5: FY2025
A6: Assets
A7: Cash and cash equivalents | B7: ='Cash Flow'!B21 -> 3794.6298 | C7: ='Cash Flow'!C21 -> 1500 | D7: ='Cash Flow'!D21 -> 2528.7021
A8: Accounts receivable | B8: =(('Income Statement'!B6*'Assumptions'!B23)/365) -> 5756.2192 | C8: =(('Income Statement'!C6*'Assumptions'!B23)/365) -> 6686.6466 | D8: =(('Income Statement'!D6*'Assumptions'!B23)/365) -> 7507.9671
A9: Inventory | B9: =((('Income Statement'!B7+'Income Statement'!B8)*'Assumptions'!B24)/365) -> 5140.9932 | C9: =((('Income Statement'!C7+'Income Statement'!C8)*'Assumptions'!B24)/365) -> 6065.9726 | D9: =((('Income Statement'!D7+'Income Statement'!D8)*'Assumptions'!B24)/365) -> 7007.8619
A10: Prepaid expenses | B10: =('Income Statement'!B6*'Assumptions'!B25) -> 552.9 | C10: =('Income Statement'!C6*'Assumptions'!B25) -> 642.27 | D10: =('Income Statement'!D6*'Assumptions'!B25) -> 721.16
A11: Total current assets | B11: =(B7+B8+B9+B10) -> 15244.742 | C11: =(C7+C8+C9+C10) -> 14894.889 | D11: =(D7+D8+D9+D10) -> 17765.691
A12: Property, plant and equipment, net | B12: =(('Assumptions'!B32+'Assumptions'!B15)-'Income Statement'!B14) -> 15920 | C12: =(('Balance Sheet'!B12+'Assumptions'!C15)-'Income Statement'!C14) -> 20128 | D12: =(('Balance Sheet'!C12+'Assumptions'!D15)-'Income Statement'!D14) -> 20315.2
A13: Total assets | B13: =(B11+B12) -> 31164.742 | C13: =(C11+C12) -> 35022.889 | D13: =(D11+D12) -> 38080.891
A14: Liabilities
A15: Accounts payable | B15: =((('Income Statement'!B7+'Income Statement'!B8)*'Assumptions'!B26)/365) -> 4206.2671 | C15: =((('Income Statement'!C7+'Income Statement'!C8)*'Assumptions'!B26)/365) -> 4963.0685 | D15: =((('Income Statement'!D7+'Income Statement'!D8)*'Assumptions'!B26)/365) -> 5733.7052
A16: Accrued liabilities | B16: =('Income Statement'!B6*'Assumptions'!B27) -> 2211.6 | C16: =('Income Statement'!C6*'Assumptions'!B27) -> 2569.08 | D16: =('Income Statement'!D6*'Assumptions'!B27) -> 2884.64
A17: Total current liabilities | B17: =(B15+B16) -> 6417.8671 | C17: =(C15+C16) -> 7532.1485 | D17: =(D15+D16) -> 8618.3452
A18: Revolver | B18: =(('Assumptions'!B35+MAX(0,MIN(('Assumptions'!B21-((('Assumptions'!B28+'Cash Flow'!B13)+'Cash Flow'!B15)+'Cash Flow'!B16)),('Assumptions'!B19-'Assumptions'!B35))))-MAX(0,MIN('Assumptions'!B35,(((('Assumptions'!B28+'Cash Flow'!B13)+'Cash Flow'!B15)+'Cash Flow'!B16)-'Assumptions'!B21)))) -> 0 | C18: =(('Balance Sheet'!B18+MAX(0,MIN(('Assumptions'!B21-((('Balance Sheet'!B7+'Cash Flow'!C13)+'Cash Flow'!C15)+'Cash Flow'!C16)),('Assumptions'!B19-'Balance Sheet'!B18))))-MAX(0,MIN('Balance Sheet'!B18,(((('Balance Sheet'!B7+'Cash Flow'!C13)+'Cash Flow'!C15)+'Cash Flow'!C16)-'Assumptions'!B21)))) -> 122.71693 | D18: =(('Balance Sheet'!C18+MAX(0,MIN(('Assumptions'!B21-((('Balance Sheet'!C7+'Cash Flow'!D13)+'Cash Flow'!D15)+'Cash Flow'!D16)),('Assumptions'!B19-'Balance Sheet'!C18))))-MAX(0,MIN('Balance Sheet'!C18,(((('Balance Sheet'!C7+'Cash Flow'!D13)+'Cash Flow'!D15)+'Cash Flow'!D16)-'Assumptions'!B21)))) -> 0
A19: Equipment loan | B19: =('Assumptions'!B36-'Assumptions'!B17) -> 7500 | C19: =('Balance Sheet'!B19-'Assumptions'!B17) -> 6000 | D19: =('Balance Sheet'!C19-'Assumptions'!B17) -> 4500
A20: Total liabilities | B20: =((B17+B18)+B19) -> 13917.867 | C20: =((C17+C18)+C19) -> 13654.865 | D20: =((D17+D18)+D19) -> 13118.345
A21: Equity
A22: Common stock and paid in capital | B22: ='Assumptions'!B37 -> 6000 | C22: ='Assumptions'!B37 -> 6000 | D22: ='Assumptions'!B37 -> 6000
A23: Retained earnings | B23: =('Assumptions'!B38+'Income Statement'!B19) -> 11246.875 | C23: =(B23+'Income Statement'!C19) -> 15368.024 | D23: =(C23+'Income Statement'!D19) -> 18962.546
A24: Total equity | B24: =(B22+B23) -> 17246.875 | C24: =(C22+C23) -> 21368.024 | D24: =(D22+D23) -> 24962.546
A25: Total liabilities and equity | B25: =(B20+B24) -> 31164.742 | C25: =(C20+C24) -> 35022.889 | D25: =(D20+D24) -> 38080.891

Sheet Cash Flow
A1: Saltbrush Beverage Co.
A2: Cash Flow Statement
A3: ($ in thousands, except per case amounts) For the years ended December 31
B5: FY2023 | C5: FY2024 | D5: FY2025
A6: Net income | B6: ='Income Statement'!B19 -> 3946.875 | C6: ='Income Statement'!C19 -> 4121.1487 | D6: ='Income Statement'!D19 -> 3594.5222
A7: Depreciation | B7: ='Income Statement'!B14 -> 1480 | C7: ='Income Statement'!C14 -> 1592 | D7: ='Income Statement'!D14 -> 2012.8
A8: (Increase) decrease in accounts receivable | B8: =(-('Balance Sheet'!B8-'Assumptions'!B29)) -> -456.21918 | C8: =(-('Balance Sheet'!C8-'Balance Sheet'!B8)) -> -930.4274 | D8: =(-('Balance Sheet'!D8-'Balance Sheet'!C8)) -> -821.32055
A9: (Increase) decrease in inventory | B9: =(-('Balance Sheet'!B9-'Assumptions'!B30)) -> -240.99315 | C9: =(-('Balance Sheet'!C9-'Balance Sheet'!B9)) -> -924.97945 | D9: =(-('Balance Sheet'!D9-'Balance Sheet'!C9)) -> -941.88932
A10: (Increase) decrease in prepaid expenses | B10: =(-('Balance Sheet'!B10-'Assumptions'!B31)) -> -52.9 | C10: =(-('Balance Sheet'!C10-'Balance Sheet'!B10)) -> -89.37 | D10: =(-('Balance Sheet'!D10-'Balance Sheet'!C10)) -> -78.89
A11: Increase (decrease) in accounts payable | B11: =('Balance Sheet'!B15-'Assumptions'!B33) -> 506.26712 | C11: =('Balance Sheet'!C15-'Balance Sheet'!B15) -> 756.80137 | D11: =('Balance Sheet'!D15-'Balance Sheet'!C15) -> 770.63671
A12: Increase (decrease) in accrued liabilities | B12: =('Balance Sheet'!B16-'Assumptions'!B34) -> 311.6 | C12: =('Balance Sheet'!C16-'Balance Sheet'!B16) -> 357.48 | D12: =('Balance Sheet'!D16-'Balance Sheet'!C16) -> 315.56
A13: Cash from operating activities | B13: =(B6+B7+B8+B9+B10+B11+B12) -> 5494.6298 | C13: =(C6+C7+C8+C9+C10+C11+C12) -> 4882.6533 | D13: =(D6+D7+D8+D9+D10+D11+D12) -> 4851.419
A14: Capital expenditures | B14: =(-'Assumptions'!B15) -> -2600 | C14: =(-'Assumptions'!C15) -> -5800 | D14: =(-'Assumptions'!D15) -> -2200
A15: Cash from investing activities | B15: =B14 -> -2600 | C15: =C14 -> -5800 | D15: =D14 -> -2200
A16: Equipment loan repayment | B16: =(-'Assumptions'!B17) -> -1500 | C16: =(-'Assumptions'!B17) -> -1500 | D16: =(-'Assumptions'!B17) -> -1500
A17: Revolver draw (repayment) | B17: =(MAX(0,MIN(('Assumptions'!B21-((('Assumptions'!B28+B13)+B15)+B16)),('Assumptions'!B19-'Assumptions'!B35)))-MAX(0,MIN('Assumptions'!B35,(((('Assumptions'!B28+B13)+B15)+B16)-'Assumptions'!B21)))) -> 0 | C17: =(MAX(0,MIN(('Assumptions'!B21-((('Balance Sheet'!B7+C13)+C15)+C16)),('Assumptions'!B19-'Balance Sheet'!B18)))-MAX(0,MIN('Balance Sheet'!B18,(((('Balance Sheet'!B7+C13)+C15)+C16)-'Assumptions'!B21)))) -> 122.71693 | D17: =(MAX(0,MIN(('Assumptions'!B21-((('Balance Sheet'!C7+D13)+D15)+D16)),('Assumptions'!B19-'Balance Sheet'!C18)))-MAX(0,MIN('Balance Sheet'!C18,(((('Balance Sheet'!C7+D13)+D15)+D16)-'Assumptions'!B21)))) -> -122.71693
A18: Cash from financing activities | B18: =(B16+B17) -> -1500 | C18: =(C16+C17) -> -1377.2831 | D18: =(D16+D17) -> -1622.7169
A19: Net change in cash | B19: =((B13+B15)+B18) -> 1394.6298 | C19: =((C13+C15)+C18) -> -2294.6298 | D19: =((D13+D15)+D18) -> 1028.7021
A20: Beginning cash | B20: ='Assumptions'!B28 -> 2400 | C20: ='Balance Sheet'!B7 -> 3794.6298 | D20: ='Balance Sheet'!C7 -> 1500
A21: Ending cash | B21: =(B20+B19) -> 3794.6298 | C21: =(C20+C19) -> 1500 | D21: =(D20+D19) -> 2528.7021
B24: FY2023 | C24: FY2024 | D24: FY2025
A25: Cash before revolver | B25: =((('Assumptions'!B28+B13)+B15)+B16) -> 3794.6298 | C25: =((('Balance Sheet'!B7+C13)+C15)+C16) -> 1377.2831 | D25: =((('Balance Sheet'!C7+D13)+D15)+D16) -> 2651.419

Sheet Ratios
A1: Saltbrush Beverage Co.
A2: Ratios
A3: ($ in thousands, except per case amounts)
B5: FY2023 | C5: FY2024 | D5: FY2025
A6: Gross margin | B6: =('Income Statement'!B9/'Income Statement'!B6) -> 0.38293543 | C6: =('Income Statement'!C9/'Income Statement'!C6) -> 0.3732231 | D6: =('Income Statement'!D9/'Income Statement'!D6) -> 0.35511232
A7: EBITDA margin | B7: =('Income Statement'!B13/'Income Statement'!B6) -> 0.13293543 | C7: =('Income Statement'!C13/'Income Statement'!C6) -> 0.1182231 | D7: =('Income Statement'!D13/'Income Statement'!D6) -> 0.10011232
A8: Operating margin | B8: =('Income Statement'!B15/'Income Statement'!B6) -> 0.10616748 | C8: =('Income Statement'!C15/'Income Statement'!C6) -> 0.093436016 | D8: =('Income Statement'!D15/'Income Statement'!D6) -> 0.072201731
A9: Net margin | B9: =('Income Statement'!B19/'Income Statement'!B6) -> 0.07138497 | C9: =('Income Statement'!C19/'Income Statement'!C6) -> 0.064165363 | D9: =('Income Statement'!D19/'Income Statement'!D6) -> 0.049843615
A10: Revenue growth | B10: n/a | C10: =(('Income Statement'!C6/'Income Statement'!B6)-1) -> 0.16163863 | D10: =(('Income Statement'!D6/'Income Statement'!C6)-1) -> 0.12282996
A11: Current ratio | B11: =('Balance Sheet'!B11/'Balance Sheet'!B17) -> 2.3753596 | C11: =('Balance Sheet'!C11/'Balance Sheet'!C17) -> 1.9775087 | D11: =('Balance Sheet'!D11/'Balance Sheet'!D17) -> 2.0613808
A12: Debt to EBITDA | B12: =(('Balance Sheet'!B18+'Balance Sheet'!B19)/'Income Statement'!B13) -> 1.0204082 | C12: =(('Balance Sheet'!C18+'Balance Sheet'!C19)/'Income Statement'!C13) -> 0.80635114 | D12: =(('Balance Sheet'!D18+'Balance Sheet'!D19)/'Income Statement'!D13) -> 0.6232946
A13: Return on equity | B13: =('Income Statement'!B19/((('Assumptions'!B37+'Assumptions'!B38)+'Balance Sheet'!B24)/2)) -> 0.25841432 | C13: =('Income Statement'!C19/(('Balance Sheet'!B24+'Balance Sheet'!C24)/2)) -> 0.21344864 | D13: =('Income Statement'!D19/(('Balance Sheet'!C24+'Balance Sheet'!D24)/2)) -> 0.15516849
A14: Days sales outstanding | B14: =(('Balance Sheet'!B8/'Income Statement'!B6)*365) -> 38 | C14: =(('Balance Sheet'!C8/'Income Statement'!C6)*365) -> 38 | D14: =(('Balance Sheet'!D8/'Income Statement'!D6)*365) -> 38
A15: Days inventory outstanding | B15: =(('Balance Sheet'!B9/('Income Statement'!B7+'Income Statement'!B8))*365) -> 55 | C15: =(('Balance Sheet'!C9/('Income Statement'!C7+'Income Statement'!C8))*365) -> 55 | D15: =(('Balance Sheet'!D9/('Income Statement'!D7+'Income Statement'!D8))*365) -> 55
A16: Days payable outstanding | B16: =(('Balance Sheet'!B15/('Income Statement'!B7+'Income Statement'!B8))*365) -> 45 | C16: =(('Balance Sheet'!C15/('Income Statement'!C7+'Income Statement'!C8))*365) -> 45 | D16: =(('Balance Sheet'!D15/('Income Statement'!D7+'Income Statement'!D8))*365) -> 45
A17: Cash conversion cycle | B17: =((B14+B15)-B16) -> 48 | C17: =((C14+C15)-C16) -> 48 | D17: =((D14+D15)-D16) -> 48
A18: Free cash flow | B18: =('Cash Flow'!B13+'Cash Flow'!B14) -> 2894.6298 | C18: =('Cash Flow'!C13+'Cash Flow'!C14) -> -917.34673 | D18: =('Cash Flow'!D13+'Cash Flow'!D14) -> 2651.419
A19: FCF margin | B19: =(('Cash Flow'!B13+'Cash Flow'!B14)/'Income Statement'!B6) -> 0.052353586 | C19: =(('Cash Flow'!C13+'Cash Flow'!C14)/'Income Statement'!C6) -> -0.014282883 | D19: =(('Cash Flow'!D13+'Cash Flow'!D14)/'Income Statement'!D6) -> 0.03676603

Sheet Variances
A1: Saltbrush Beverage Co.
A2: FY2025 standard cost variances
A3: ($ in thousands, except per case amounts)
B5: Amount | C5: U/F
A6: Cans and ends (units): price variance | B6: =((0.163-0.155)*145900) -> 1167.2 | C6: U
A7: Cans and ends (units): usage variance | B7: =((145900-(24*'Assumptions'!D6))*0.155) -> 443.3 | C7: U
A8: Botanicals and flavor (kg): price variance | B8: =((11.35-11.6)*305) -> -76.25 | C8: F
A9: Botanicals and flavor (kg): usage variance | B9: =((305-(0.05*'Assumptions'!D6))*11.6) -> 81.2 | C9: U
A10: Juice concentrate (gallons): price variance | B10: =((9.4-9)*243.6) -> 97.44 | C10: U
A11: Juice concentrate (gallons): usage variance | B11: =((243.6-(0.04*'Assumptions'!D6))*9) -> 46.8 | C11: U
A12: Trays and film (sets): price variance | B12: =((0.43-0.44)*6050) -> -60.5 | C12: F
A13: Trays and film (sets): usage variance | B13: =((6050-(1*'Assumptions'!D6))*0.44) -> 39.6 | C13: U
A14: Labor: rate variance | B14: =((29.1-27.5)*118.4) -> 189.44 | C14: U
A15: Labor: efficiency variance | B15: =((118.4-(0.0189*'Assumptions'!D6))*27.5) -> 158.29 | C15: U
A16: Overhead: spending variance | B16: =(10925-10800) -> 125 | C16: U
A17: Overhead: volume variance | B17: =(10800-(1.8*'Assumptions'!D6)) -> 72 | C17: U
A18: Total manufacturing variances | B18: =(((0.163-0.155)*145900)+((145900-(24*'Assumptions'!D6))*0.155)+((11.35-11.6)*305)+((305-(0.05*'Assumptions'!D6))*11.6)+((9.4-9)*243.6)+((243.6-(0.04*'Assumptions'!D6))*9)+((0.43-0.44)*6050)+((6050-(1*'Assumptions'!D6))*0.44)+((29.1-27.5)*118.4)+((118.4-(0.0189*'Assumptions'!D6))*27.5)+(10925-10800)+(10800-(1.8*'Assumptions'!D6))) -> 2283.52 | C18: U

Sheet Margin Bridge
A1: Saltbrush Beverage Co.
A2: Gross profit bridge, FY2024 to FY2025
A3: ($ in thousands, except per case amounts)
B5: Amount
A6: FY2024 gross profit | B6: ='Income Statement'!C9 -> 23971
A7: Volume effect | B7: =(('Assumptions'!D6-'Assumptions'!C6)*('Assumptions'!C7-'Assumptions'!C8)) -> 2457
A8: Price effect | B8: =(('Assumptions'!D7-'Assumptions'!C7)*'Assumptions'!D6) -> 1490
A9: Standard cost effect | B9: =((-('Assumptions'!D8-'Assumptions'!C8))*'Assumptions'!D6) -> -715.2
A10: Variance effect | B10: =(-('Income Statement'!D8-'Income Statement'!C8)) -> -1593.52
A11: FY2025 gross profit | B11: ='Income Statement'!D9 -> 25609.28
A12: Check: steps sum to the change in gross profit | B12: =(((((B6+B7)+B8)+B9)+B10)-B11) -> -3.6379788e-12

Sheet 13 Week Cash
A1: Saltbrush Beverage Co.
A2: 13 week cash forecast, Q1 FY2026
A3: ($ in thousands, except per case amounts)
B5: Jan 9 | C5: Jan 16 | D5: Jan 23 | E5: Jan 30 | F5: Feb 6 | G5: Feb 13 | H5: Feb 20 | I5: Feb 27 | J5: Mar 6 | K5: Mar 13 | L5: Mar 20 | M5: Mar 27 | N5: Apr 3
A6: Beginning cash | B6: ='Cash Flow'!D21 -> 2528.7021 | C6: =B19 -> 2133.7021 | D6: =C19 -> 2203.7021 | E6: =D19 -> 1973.7021 | F6: =E19 -> 2333.7021 | G6: =F19 -> 1978.7021 | H6: =G19 -> 2038.7021 | I6: =H19 -> 1808.7021 | J6: =I19 -> 1738.7021 | ... N6: =M19 -> 1500
A7: Receipts | B7: =1280 -> 1280 | C7: =1310 -> 1310 | D7: =1390 -> 1390 | E7: =1350 -> 1350 | F7: =1300 -> 1300 | G7: =1340 -> 1340 | H7: =1410 -> 1410 | I7: =1380 -> 1380 | J7: =1360 -> 1360 | K7: =1420 -> 1420 | L7: =1450 -> 1450 | M7: =1470 -> 1470 | N7: =1500 -> 1500
A8: Suppliers | B8: =820 -> 820 | C8: =790 -> 790 | D8: =860 -> 860 | E8: =840 -> 840 | F8: =800 -> 800 | G8: =830 -> 830 | H8: =880 -> 880 | I8: =850 -> 850 | J8: =840 -> 840 | K8: =870 -> 870 | L8: =890 -> 890 | M8: =900 -> 900 | N8: =910 -> 910
A9: Payroll | B9: =610 -> 610 | C9: =0 -> 0 | D9: =610 -> 610 | E9: =0 -> 0 | F9: =610 -> 610 | G9: =0 -> 0 | H9: =610 -> 610 | I9: =0 -> 0 | J9: =610 -> 610 | K9: =0 -> 0 | L9: =610 -> 610 | M9: =0 -> 0 | N9: =610 -> 610
A10: Freight | B10: =150 -> 150 | C10: =150 -> 150 | D10: =150 -> 150 | E10: =150 -> 150 | F10: =150 -> 150 | G10: =150 -> 150 | H10: =150 -> 150 | I10: =150 -> 150 | ... N10: =150 -> 150
A11: Rent | B11: =95 -> 95 | C11: =0 -> 0 | D11: =0 -> 0 | E11: =0 -> 0 | F11: =95 -> 95 | G11: =0 -> 0 | H11: =0 -> 0 | I11: =0 -> 0 | J11: =95 -> 95 | K11: =0 -> 0 | L11: =0 -> 0 | M11: =0 -> 0 | N11: =0 -> 0
A12: Trade promotions | B12: =0 -> 0 | C12: =300 -> 300 | D12: =0 -> 0 | E12: =0 -> 0 | F12: =0 -> 0 | G12: =300 -> 300 | H12: =0 -> 0 | I12: =0 -> 0 | J12: =0 -> 0 | K12: =300 -> 300 | L12: =0 -> 0 | M12: =0 -> 0 | N12: =0 -> 0
A13: Estimated tax | B13: =0 -> 0 | C13: =0 -> 0 | D13: =0 -> 0 | E13: =0 -> 0 | F13: =0 -> 0 | G13: =0 -> 0 | H13: =0 -> 0 | I13: =0 -> 0 | ... K13: =0 -> 0 | L13: =900 -> 900 | M13: =0 -> 0 | N13: =0 -> 0
A14: Capital expenditures | B14: =0 -> 0 | C14: =0 -> 0 | D14: =0 -> 0 | E14: =0 -> 0 | F14: =0 -> 0 | G14: =0 -> 0 | H14: =0 -> 0 | I14: =450 -> 450 | J14: =0 -> 0 | K14: =0 -> 0 | L14: =0 -> 0 | M14: =0 -> 0 | N14: =0 -> 0
A15: Debt service (principal and interest) | B15: =0 -> 0 | C15: =0 -> 0 | D15: =0 -> 0 | E15: =0 -> 0 | F15: =0 -> 0 | G15: =0 -> 0 | H15: =0 -> 0 | I15: =0 -> 0 | ... M15: =0 -> 0 | N15: =((('Assumptions'!B17*0)+375)+('Balance Sheet'!D19*('Assumptions'!B18/4))) -> 450.9375
A16: Total disbursements | B16: =(B8+B9+B10+B11+B12+B13+B14+B15) -> 1675 | C16: =(C8+C9+C10+C11+C12+C13+C14+C15) -> 1240 | D16: =(D8+D9+D10+D11+D12+D13+D14+D15) -> 1620 | E16: =(E8+E9+E10+E11+E12+E13+E14+E15) -> 990 | F16: =(F8+F9+F10+F11+F12+F13+F14+F15) -> 1655 | G16: =(G8+G9+G10+G11+G12+G13+G14+G15) -> 1280 | H16: =(H8+H9+H10+H11+H12+H13+H14+H15) -> 1640 | I16: =(I8+I9+I10+I11+I12+I13+I14+I15) -> 1450 | ... N16: =(N8+N9+N10+N11+N12+N13+N14+N15) -> 2120.9375
A17: Net cash flow | B17: =(B7-B16) -> -395 | C17: =(C7-C16) -> 70 | D17: =(D7-D16) -> -230 | E17: =(E7-E16) -> 360 | F17: =(F7-F16) -> -355 | G17: =(G7-G16) -> 60 | H17: =(H7-H16) -> -230 | I17: =(I7-I16) -> -70 | ... N17: =(N7-N16) -> -620.9375
A18: Revolver draw (repayment) | B18: =(MAX(0,MIN(('Assumptions'!B21-(B6+B17)),('Assumptions'!B19-'Balance Sheet'!D18)))-MAX(0,MIN('Balance Sheet'!D18,((B6+B17)-'Assumptions'!B21)))) -> 0 | C18: =(MAX(0,MIN(('Assumptions'!B21-(C6+C17)),('Assumptions'!B19-B20)))-MAX(0,MIN(B20,((C6+C17)-'Assumptions'!B21)))) -> 0 | D18: =(MAX(0,MIN(('Assumptions'!B21-(D6+D17)),('Assumptions'!B19-C20)))-MAX(0,MIN(C20,((D6+D17)-'Assumptions'!B21)))) -> 0 | E18: =(MAX(0,MIN(('Assumptions'!B21-(E6+E17)),('Assumptions'!B19-D20)))-MAX(0,MIN(D20,((E6+E17)-'Assumptions'!B21)))) -> 0 | F18: =(MAX(0,MIN(('Assumptions'!B21-(F6+F17)),('Assumptions'!B19-E20)))-MAX(0,MIN(E20,((F6+F17)-'Assumptions'!B21)))) -> 0 | G18: =(MAX(0,MIN(('Assumptions'!B21-(G6+G17)),('Assumptions'!B19-F20)))-MAX(0,MIN(F20,((G6+G17)-'Assumptions'!B21)))) -> 0 | H18: =(MAX(0,MIN(('Assumptions'!B21-(H6+H17)),('Assumptions'!B19-G20)))-MAX(0,MIN(G20,((H6+H17)-'Assumptions'!B21)))) -> 0 | I18: =(MAX(0,MIN(('Assumptions'!B21-(I6+I17)),('Assumptions'!B19-H20)))-MAX(0,MIN(H20,((I6+I17)-'Assumptions'!B21)))) -> 0 | J18: =(MAX(0,MIN(('Assumptions'!B21-(J6+J17)),('Assumptions'!B19-I20)))-MAX(0,MIN(I20,((J6+J17)-'Assumptions'!B21)))) -> 96.297913 | K18: =(MAX(0,MIN(('Assumptions'!B21-(K6+K17)),('Assumptions'!B19-J20)))-MAX(0,MIN(J20,((K6+K17)-'Assumptions'!B21)))) -> -96.297913 | L18: =(MAX(0,MIN(('Assumptions'!B21-(L6+L17)),('Assumptions'!B19-K20)))-MAX(0,MIN(K20,((L6+L17)-'Assumptions'!B21)))) -> 1096.2979 | M18: =(MAX(0,MIN(('Assumptions'!B21-(M6+M17)),('Assumptions'!B19-L20)))-MAX(0,MIN(L20,((M6+M17)-'Assumptions'!B21)))) -> -420 | N18: =(MAX(0,MIN(('Assumptions'!B21-(N6+N17)),('Assumptions'!B19-M20)))-MAX(0,MIN(M20,((N6+N17)-'Assumptions'!B21)))) -> 620.9375
A19: Ending cash | B19: =((B6+B17)+B18) -> 2133.7021 | C19: =((C6+C17)+C18) -> 2203.7021 | D19: =((D6+D17)+D18) -> 1973.7021 | E19: =((E6+E17)+E18) -> 2333.7021 | F19: =((F6+F17)+F18) -> 1978.7021 | G19: =((G6+G17)+G18) -> 2038.7021 | H19: =((H6+H17)+H18) -> 1808.7021 | I19: =((I6+I17)+I18) -> 1738.7021 | ... N19: =((N6+N17)+N18) -> 1500
A20: Revolver balance | B20: =('Balance Sheet'!D18+B18) -> 0 | C20: =(B20+C18) -> 0 | D20: =(C20+D18) -> 0 | E20: =(D20+E18) -> 0 | F20: =(E20+F18) -> 0 | G20: =(F20+G18) -> 0 | H20: =(G20+H18) -> 0 | I20: =(H20+I18) -> 0 | J20: =(I20+J18) -> 96.297913 | ... N20: =(M20+N18) -> 1297.2354
A21: Availability | B21: =('Assumptions'!B19-B20) -> 8000 | C21: =('Assumptions'!B19-C20) -> 8000 | D21: =('Assumptions'!B19-D20) -> 8000 | E21: =('Assumptions'!B19-E20) -> 8000 | F21: =('Assumptions'!B19-F20) -> 8000 | G21: =('Assumptions'!B19-G20) -> 8000 | H21: =('Assumptions'!B19-H20) -> 8000 | I21: =('Assumptions'!B19-I20) -> 8000 | J21: =('Assumptions'!B19-J20) -> 7903.7021 | K21: =('Assumptions'!B19-K20) -> 8000 | L21: =('Assumptions'!B19-L20) -> 6903.7021 | M21: =('Assumptions'!B19-M20) -> 7323.7021 | N21: =('Assumptions'!B19-N20) -> 6702.7646

Sheet Checks
A1: Checks
A3: Overall status | B3: =IF(COUNTIF(C5:C26,"CHECK")=0,"ALL OK","CHECK FAILURES") -> ALL OK
A4: Check | B4: Difference | C4: Status
A5: Balance sheet balances, FY2023 | B5: =('Balance Sheet'!B13)-('Balance Sheet'!B25) -> 0 | C5: =IF(ABS(B5)<0.5,"OK","CHECK") -> OK
A6: Balance sheet balances, FY2024 | B6: =('Balance Sheet'!C13)-('Balance Sheet'!C25) -> 7.2759576e-12 | C6: =IF(ABS(B6)<0.5,"OK","CHECK") -> OK
A7: Balance sheet balances, FY2025 | B7: =('Balance Sheet'!D13)-('Balance Sheet'!D25) -> 0 | C7: =IF(ABS(B7)<0.5,"OK","CHECK") -> OK
A8: Cash flow ending cash = balance sheet cash, FY2023 | B8: =('Cash Flow'!B21)-('Balance Sheet'!B7) -> 0 | C8: =IF(ABS(B8)<0.5,"OK","CHECK") -> OK
A9: Cash flow ending cash = balance sheet cash, FY2024 | B9: =('Cash Flow'!C21)-('Balance Sheet'!C7) -> 0 | C9: =IF(ABS(B9)<0.5,"OK","CHECK") -> OK
A10: Cash flow ending cash = balance sheet cash, FY2025 | B10: =('Cash Flow'!D21)-('Balance Sheet'!D7) -> 0 | C10: =IF(ABS(B10)<0.5,"OK","CHECK") -> OK
A11: Net income ties, income statement to cash flow, FY2023 | B11: =('Income Statement'!B19)-('Cash Flow'!B6) -> 0 | C11: =IF(ABS(B11)<0.5,"OK","CHECK") -> OK
A12: Net income ties, income statement to cash flow, FY2024 | B12: =('Income Statement'!C19)-('Cash Flow'!C6) -> 0 | C12: =IF(ABS(B12)<0.5,"OK","CHECK") -> OK
A13: Net income ties, income statement to cash flow, FY2025 | B13: =('Income Statement'!D19)-('Cash Flow'!D6) -> 0 | C13: =IF(ABS(B13)<0.5,"OK","CHECK") -> OK
A14: Beginning cash equals prior year ending cash, FY2023 | B14: =('Cash Flow'!B20)-('Assumptions'!B28) -> 0 | C14: =IF(ABS(B14)<0.5,"OK","CHECK") -> OK
A15: Beginning cash equals prior year ending cash, FY2024 | B15: =('Cash Flow'!C20)-('Cash Flow'!B21) -> 0 | C15: =IF(ABS(B15)<0.5,"OK","CHECK") -> OK
A16: Beginning cash equals prior year ending cash, FY2025 | B16: =('Cash Flow'!D20)-('Cash Flow'!C21) -> 0 | C16: =IF(ABS(B16)<0.5,"OK","CHECK") -> OK
A17: Retained earnings rolls forward, FY2023 | B17: =('Balance Sheet'!B23)-(('Assumptions'!B38+'Income Statement'!B19)) -> 0 | C17: =IF(ABS(B17)<0.5,"OK","CHECK") -> OK
A18: Retained earnings rolls forward, FY2024 | B18: =('Balance Sheet'!C23)-(('Balance Sheet'!B23+'Income Statement'!C19)) -> 0 | C18: =IF(ABS(B18)<0.5,"OK","CHECK") -> OK
A19: Retained earnings rolls forward, FY2025 | B19: =('Balance Sheet'!D23)-(('Balance Sheet'!C23+'Income Statement'!D19)) -> 0 | C19: =IF(ABS(B19)<0.5,"OK","CHECK") -> OK
A20: Total current assets equal their components, FY2023 | B20: =('Balance Sheet'!B11)-(('Balance Sheet'!B7+'Balance Sheet'!B8+'Balance Sheet'!B9+'Balance Sheet'!B10)) -> 0 | C20: =IF(ABS(B20)<0.5,"OK","CHECK") -> OK
A21: Total current assets equal their components, FY2024 | B21: =('Balance Sheet'!C11)-(('Balance Sheet'!C7+'Balance Sheet'!C8+'Balance Sheet'!C9+'Balance Sheet'!C10)) -> 0 | C21: =IF(ABS(B21)<0.5,"OK","CHECK") -> OK
A22: Total current assets equal their components, FY2025 | B22: =('Balance Sheet'!D11)-(('Balance Sheet'!D7+'Balance Sheet'!D8+'Balance Sheet'!D9+'Balance Sheet'!D10)) -> 0 | C22: =IF(ABS(B22)<0.5,"OK","CHECK") -> OK
A23: Total liabilities equal their components, FY2023 | B23: =('Balance Sheet'!B20)-((('Balance Sheet'!B17+'Balance Sheet'!B18)+'Balance Sheet'!B19)) -> 0 | C23: =IF(ABS(B23)<0.5,"OK","CHECK") -> OK
A24: Total liabilities equal their components, FY2024 | B24: =('Balance Sheet'!C20)-((('Balance Sheet'!C17+'Balance Sheet'!C18)+'Balance Sheet'!C19)) -> 0 | C24: =IF(ABS(B24)<0.5,"OK","CHECK") -> OK
A25: Total liabilities equal their components, FY2025 | B25: =('Balance Sheet'!D20)-((('Balance Sheet'!D17+'Balance Sheet'!D18)+'Balance Sheet'!D19)) -> 0 | C25: =IF(ABS(B25)<0.5,"OK","CHECK") -> OK
A26: Margin bridge steps sum to the change in gross profit | B26: =('Margin Bridge'!B12)-(0) -> -3.6379788e-12 | C26: =IF(ABS(B26)<0.5,"OK","CHECK") -> OK
