Workbook

Sheet Cover
A2: Aldercrest Aerospace, Inc.
A4: Composite wing and fuselage panels for defense aircraft programs
A6: Fiscal years covered: FY2023, FY2024, FY2025
A8: Industry: Aerospace and defense supplier
A9: Role fit: Program finance, Cost analysis, FP&A
A11: Fictional company. All figures are illustrative and were built for this portfolio.
A12: Prepared by George Murad
A14: Contents
A15: Cover
A16: Assumptions
A17: Income Statement
A18: Balance Sheet
... A29: Formula, pulls from another sheet

Sheet Assumptions
A1: Aldercrest Aerospace, Inc.
A2: Assumptions
A3: ($ in thousands)
B5: FY2023 | C5: FY2024 | D5: FY2025
A6: Total revenue | B6: 142600 | C6: 163900 | D6: 184250
A7: Defense share of revenue | B7: 0.72 | C7: 0.74 | D7: 0.76
A8: Gross margin | B8: 0.215 | C8: 0.22 | D8: 0.206
A9: General and administrative, % of revenue | B9: 0.052
A10: Bid and proposal and IR&D, % of revenue | B10: 0.018
A11: Selling, % of revenue | B11: 0.01
A12: Depreciation, % of beginning net PP&E | B12: 0.12
A13: Amortization of intangibles, per year | B13: 800
A14: Capital expenditures | B14: 9800 | C14: 12400 | D14: 14100
A15: Term loan, opening balance | B15: 44000
A16: Term loan, annual repayment | B16: 4000
A17: Term loan interest rate | B17: 0.0725
A18: Revolver capacity | B18: 25000
A19: Revolver interest rate | B19: 0.08
A20: Minimum cash | B20: 8000
A21: Income tax rate | B21: 0.24
A22: Accounts receivable days | B22: 48
A23: Contract assets, % of revenue | B23: 0.11 | C23: 0.115 | D23: 0.125
A24: Inventory days | B24: 62
A25: Prepaid expenses, % of revenue | B25: 0.013
A26: Accounts payable days | B26: 41
A27: Accrued liabilities, % of revenue | B27: 0.055
A28: Contract liabilities, % of revenue | B28: 0.03
A29: Opening balance sheet FY2022: Cash | B29: 9500
A30: Opening balance sheet FY2022: Accounts receivable | B30: 17000
A31: Opening balance sheet FY2022: Contract assets | B31: 14500
A32: Opening balance sheet FY2022: Inventory | B32: 20000
A33: Opening balance sheet FY2022: Prepaid expenses | B33: 1800
A34: Opening balance sheet FY2022: Property, plant and equipment, net | B34: 62000
A35: Opening balance sheet FY2022: Intangible assets | B35: 8000
... A42: Opening balance sheet FY2022: Retained earnings | B42: 40200
A43: Bookings | B43: 168400 | C43: 181200 | D43: 171900
A44: Backlog, start of FY2023 | B44: 285000

Sheet Income Statement
A1: Aldercrest Aerospace, Inc.
A2: Income Statement
A3: ($ in thousands) For the years ended December 31
B5: FY2023 | C5: FY2024 | D5: FY2025
A6: Defense programs | B6: =('Assumptions'!B6*'Assumptions'!B7) -> 102672 | C6: =('Assumptions'!C6*'Assumptions'!C7) -> 121286 | D6: =('Assumptions'!D6*'Assumptions'!D7) -> 140030
A7: Commercial aerospace | B7: =('Assumptions'!B6*(1-'Assumptions'!B7)) -> 39928 | C7: =('Assumptions'!C6*(1-'Assumptions'!C7)) -> 42614 | D7: =('Assumptions'!D6*(1-'Assumptions'!D7)) -> 44220
A8: Total revenue | B8: =(B6+B7) -> 142600 | C8: =(C6+C7) -> 163900 | D8: =(D6+D7) -> 184250
A9: Cost of sales | B9: =(B8*(1-'Assumptions'!B8)) -> 111941 | C9: =(C8*(1-'Assumptions'!C8)) -> 127842 | D9: =(D8*(1-'Assumptions'!D8)) -> 146294.5
A10: Gross profit | B10: =(B8-B9) -> 30659 | C10: =(C8-C9) -> 36058 | D10: =(D8-D9) -> 37955.5
A11: General and administrative | B11: =(B8*'Assumptions'!B9) -> 7415.2 | C11: =(C8*'Assumptions'!B9) -> 8522.8 | D11: =(D8*'Assumptions'!B9) -> 9581
A12: Bid and proposal and IR&D | B12: =(B8*'Assumptions'!B10) -> 2566.8 | C12: =(C8*'Assumptions'!B10) -> 2950.2 | D12: =(D8*'Assumptions'!B10) -> 3316.5
A13: Selling | B13: =(B8*'Assumptions'!B11) -> 1426 | C13: =(C8*'Assumptions'!B11) -> 1639 | D13: =(D8*'Assumptions'!B11) -> 1842.5
A14: EBITDA | B14: =(((B10-B11)-B12)-B13) -> 19251 | C14: =(((C10-C11)-C12)-C13) -> 22946 | D14: =(((D10-D11)-D12)-D13) -> 23215.5
A15: Depreciation and amortization | B15: =(('Assumptions'!B34*'Assumptions'!B12)+'Assumptions'!B13) -> 8240 | C15: =(('Balance Sheet'!B13*'Assumptions'!B12)+'Assumptions'!B13) -> 8523.2 | D15: =(('Balance Sheet'!C13*'Assumptions'!B12)+'Assumptions'!B13) -> 9084.416
A16: Operating income | B16: =(B14-B15) -> 11011 | C16: =(C14-C15) -> 14422.8 | D16: =(D14-D15) -> 14131.084
A17: Interest expense | B17: =(('Assumptions'!B40*'Assumptions'!B17)+('Assumptions'!B39*'Assumptions'!B19)) -> 3190 | C17: =(('Balance Sheet'!B22*'Assumptions'!B17)+('Balance Sheet'!B21*'Assumptions'!B19)) -> 2900 | D17: =(('Balance Sheet'!C22*'Assumptions'!B17)+('Balance Sheet'!C21*'Assumptions'!B19)) -> 2889.3982
A18: Income before taxes | B18: =(B16-B17) -> 7821 | C18: =(C16-C17) -> 11522.8 | D18: =(D16-D17) -> 11241.686
A19: Income tax expense | B19: =MAX(0,(B18*'Assumptions'!B21)) -> 1877.04 | C19: =MAX(0,(C18*'Assumptions'!B21)) -> 2765.472 | D19: =MAX(0,(D18*'Assumptions'!B21)) -> 2698.0046
A20: Net income | B20: =(B18-B19) -> 5943.96 | C20: =(C18-C19) -> 8757.328 | D20: =(D18-D19) -> 8543.6812
A21: Gross margin | B21: =(B10/B8) -> 0.215 | C21: =(C10/C8) -> 0.22 | D21: =(D10/D8) -> 0.206
A22: EBITDA margin | B22: =(B14/B8) -> 0.135 | C22: =(C14/C8) -> 0.14 | D22: =(D14/D8) -> 0.126

Sheet Balance Sheet
A1: Aldercrest Aerospace, Inc.
A2: Balance Sheet
A3: ($ in thousands) As of December 31
B5: FY2023 | C5: FY2024 | D5: FY2025
A6: Assets
A7: Cash and cash equivalents | B7: ='Cash Flow'!B23 -> 8971.8422 | C7: ='Cash Flow'!C23 -> 8000 | D7: ='Cash Flow'!D23 -> 8000
A8: Accounts receivable | B8: =(('Income Statement'!B8*'Assumptions'!B22)/365) -> 18752.877 | C8: =(('Income Statement'!C8*'Assumptions'!B22)/365) -> 21553.973 | D8: =(('Income Statement'!D8*'Assumptions'!B22)/365) -> 24230.137
A9: Contract assets (unbilled) | B9: =('Income Statement'!B8*'Assumptions'!B23) -> 15686 | C9: =('Income Statement'!C8*'Assumptions'!C23) -> 18848.5 | D9: =('Income Statement'!D8*'Assumptions'!D23) -> 23031.25
A10: Inventory | B10: =(('Income Statement'!B9*'Assumptions'!B24)/365) -> 19014.636 | C10: =(('Income Statement'!C9*'Assumptions'!B24)/365) -> 21715.627 | D10: =(('Income Statement'!D9*'Assumptions'!B24)/365) -> 24850.025
A11: Prepaid expenses | B11: =('Income Statement'!B8*'Assumptions'!B25) -> 1853.8 | C11: =('Income Statement'!C8*'Assumptions'!B25) -> 2130.7 | D11: =('Income Statement'!D8*'Assumptions'!B25) -> 2395.25
A12: Total current assets | B12: =(B7+B8+B9+B10+B11) -> 64279.155 | C12: =(C7+C8+C9+C10+C11) -> 72248.8 | D12: =(D7+D8+D9+D10+D11) -> 82506.662
A13: Property, plant and equipment, net | B13: =(('Assumptions'!B34+'Assumptions'!B14)-('Income Statement'!B15-'Assumptions'!B13)) -> 64360 | C13: =(('Balance Sheet'!B13+'Assumptions'!C14)-('Income Statement'!C15-'Assumptions'!B13)) -> 69036.8 | D13: =(('Balance Sheet'!C13+'Assumptions'!D14)-('Income Statement'!D15-'Assumptions'!B13)) -> 74852.384
A14: Intangible assets | B14: =('Assumptions'!B35-'Assumptions'!B13) -> 7200 | C14: =(B14-'Assumptions'!B13) -> 6400 | D14: =(C14-'Assumptions'!B13) -> 5600
A15: Total assets | B15: =((B12+B13)+B14) -> 135839.15 | C15: =((C12+C13)+C14) -> 147685.6 | D15: =((D12+D13)+D14) -> 162959.05
A16: Liabilities
A17: Accounts payable | B17: =(('Income Statement'!B9*'Assumptions'!B26)/365) -> 12574.195 | C17: =(('Income Statement'!C9*'Assumptions'!B26)/365) -> 14360.334 | D17: =(('Income Statement'!D9*'Assumptions'!B26)/365) -> 16433.081
A18: Accrued liabilities | B18: =('Income Statement'!B8*'Assumptions'!B27) -> 7843 | C18: =('Income Statement'!C8*'Assumptions'!B27) -> 9014.5 | D18: =('Income Statement'!D8*'Assumptions'!B27) -> 10133.75
A19: Contract liabilities (customer advances) | B19: =('Income Statement'!B8*'Assumptions'!B28) -> 4278 | C19: =('Income Statement'!C8*'Assumptions'!B28) -> 4917 | D19: =('Income Statement'!D8*'Assumptions'!B28) -> 5527.5
A20: Total current liabilities | B20: =(B17+B18+B19) -> 24695.195 | C20: =(C17+C18+C19) -> 28291.834 | D20: =(D17+D18+D19) -> 32094.331
A21: Revolver | B21: =(('Assumptions'!B39+MAX(0,MIN(('Assumptions'!B20-((('Assumptions'!B29+'Cash Flow'!B15)+'Cash Flow'!B17)+'Cash Flow'!B18)),('Assumptions'!B18-'Assumptions'!B39))))-MAX(0,MIN('Assumptions'!B39,(((('Assumptions'!B29+'Cash Flow'!B15)+'Cash Flow'!B17)+'Cash Flow'!B18)-'Assumptions'!B20)))) -> 0 | C21: =(('Balance Sheet'!B21+MAX(0,MIN(('Assumptions'!B20-((('Balance Sheet'!B7+'Cash Flow'!C15)+'Cash Flow'!C17)+'Cash Flow'!C18)),('Assumptions'!B18-'Balance Sheet'!B21))))-MAX(0,MIN('Balance Sheet'!B21,(((('Balance Sheet'!B7+'Cash Flow'!C15)+'Cash Flow'!C17)+'Cash Flow'!C18)-'Assumptions'!B20)))) -> 3492.4778 | D21: =(('Balance Sheet'!C21+MAX(0,MIN(('Assumptions'!B20-((('Balance Sheet'!C7+'Cash Flow'!D15)+'Cash Flow'!D17)+'Cash Flow'!D18)),('Assumptions'!B18-'Balance Sheet'!C21))))-MAX(0,MIN('Balance Sheet'!C21,(((('Balance Sheet'!C7+'Cash Flow'!D15)+'Cash Flow'!D17)+'Cash Flow'!D18)-'Assumptions'!B20)))) -> 10419.746
A22: Term loan | B22: =('Assumptions'!B40-'Assumptions'!B16) -> 40000 | C22: =('Balance Sheet'!B22-'Assumptions'!B16) -> 36000 | D22: =('Balance Sheet'!C22-'Assumptions'!B16) -> 32000
A23: Total liabilities | B23: =((B20+B21)+B22) -> 64695.195 | C23: =((C20+C21)+C22) -> 67784.312 | D23: =((D20+D21)+D22) -> 74514.076
A24: Equity
A25: Common stock and paid in capital | B25: ='Assumptions'!B41 -> 25000 | C25: ='Assumptions'!B41 -> 25000 | D25: ='Assumptions'!B41 -> 25000
A26: Retained earnings | B26: =('Assumptions'!B42+'Income Statement'!B20) -> 46143.96 | C26: =(B26+'Income Statement'!C20) -> 54901.288 | D26: =(C26+'Income Statement'!D20) -> 63444.969
A27: Total equity | B27: =(B25+B26) -> 71143.96 | C27: =(C25+C26) -> 79901.288 | D27: =(D25+D26) -> 88444.969
A28: Total liabilities and equity | B28: =(B23+B27) -> 135839.15 | C28: =(C23+C27) -> 147685.6 | D28: =(D23+D27) -> 162959.05

Sheet Cash Flow
A1: Aldercrest Aerospace, Inc.
A2: Cash Flow Statement
A3: ($ in thousands) For the years ended December 31
B5: FY2023 | C5: FY2024 | D5: FY2025
A6: Net income | B6: ='Income Statement'!B20 -> 5943.96 | C6: ='Income Statement'!C20 -> 8757.328 | D6: ='Income Statement'!D20 -> 8543.6812
A7: Depreciation and amortization | B7: ='Income Statement'!B15 -> 8240 | C7: ='Income Statement'!C15 -> 8523.2 | D7: ='Income Statement'!D15 -> 9084.416
A8: (Increase) decrease in accounts receivable | B8: =(-('Balance Sheet'!B8-'Assumptions'!B30)) -> -1752.8767 | C8: =(-('Balance Sheet'!C8-'Balance Sheet'!B8)) -> -2801.0959 | D8: =(-('Balance Sheet'!D8-'Balance Sheet'!C8)) -> -2676.1644
A9: (Increase) decrease in contract assets | B9: =(-('Balance Sheet'!B9-'Assumptions'!B31)) -> -1186 | C9: =(-('Balance Sheet'!C9-'Balance Sheet'!B9)) -> -3162.5 | D9: =(-('Balance Sheet'!D9-'Balance Sheet'!C9)) -> -4182.75
A10: (Increase) decrease in inventory | B10: =(-('Balance Sheet'!B10-'Assumptions'!B32)) -> 985.36438 | C10: =(-('Balance Sheet'!C10-'Balance Sheet'!B10)) -> -2700.9918 | D10: =(-('Balance Sheet'!D10-'Balance Sheet'!C10)) -> -3134.3973
A11: (Increase) decrease in prepaid expenses | B11: =(-('Balance Sheet'!B11-'Assumptions'!B33)) -> -53.8 | C11: =(-('Balance Sheet'!C11-'Balance Sheet'!B11)) -> -276.9 | D11: =(-('Balance Sheet'!D11-'Balance Sheet'!C11)) -> -264.55
A12: Increase (decrease) in accounts payable | B12: =('Balance Sheet'!B17-'Assumptions'!B36) -> 174.19452 | C12: =('Balance Sheet'!C17-'Balance Sheet'!B17) -> 1786.1397 | D12: =('Balance Sheet'!D17-'Balance Sheet'!C17) -> 2072.7466
A13: Increase (decrease) in accrued liabilities | B13: =('Balance Sheet'!B18-'Assumptions'!B37) -> 543 | C13: =('Balance Sheet'!C18-'Balance Sheet'!B18) -> 1171.5 | D13: =('Balance Sheet'!D18-'Balance Sheet'!C18) -> 1119.25
A14: Increase (decrease) in contract liabilities | B14: =('Balance Sheet'!B19-'Assumptions'!B38) -> 378 | C14: =('Balance Sheet'!C19-'Balance Sheet'!B19) -> 639 | D14: =('Balance Sheet'!D19-'Balance Sheet'!C19) -> 610.5
A15: Cash from operating activities | B15: =(B6+B7+B8+B9+B10+B11+B12+B13+B14) -> 13271.842 | C15: =(C6+C7+C8+C9+C10+C11+C12+C13+C14) -> 11935.68 | D15: =(D6+D7+D8+D9+D10+D11+D12+D13+D14) -> 11172.732
A16: Capital expenditures | B16: =(-'Assumptions'!B14) -> -9800 | C16: =(-'Assumptions'!C14) -> -12400 | D16: =(-'Assumptions'!D14) -> -14100
A17: Cash from investing activities | B17: =B16 -> -9800 | C17: =C16 -> -12400 | D17: =D16 -> -14100
A18: Term loan repayment | B18: =(-'Assumptions'!B16) -> -4000 | C18: =(-'Assumptions'!B16) -> -4000 | D18: =(-'Assumptions'!B16) -> -4000
A19: Revolver draw (repayment) | B19: =(MAX(0,MIN(('Assumptions'!B20-((('Assumptions'!B29+B15)+B17)+B18)),('Assumptions'!B18-'Assumptions'!B39)))-MAX(0,MIN('Assumptions'!B39,(((('Assumptions'!B29+B15)+B17)+B18)-'Assumptions'!B20)))) -> 0 | C19: =(MAX(0,MIN(('Assumptions'!B20-((('Balance Sheet'!B7+C15)+C17)+C18)),('Assumptions'!B18-'Balance Sheet'!B21)))-MAX(0,MIN('Balance Sheet'!B21,(((('Balance Sheet'!B7+C15)+C17)+C18)-'Assumptions'!B20)))) -> 3492.4778 | D19: =(MAX(0,MIN(('Assumptions'!B20-((('Balance Sheet'!C7+D15)+D17)+D18)),('Assumptions'!B18-'Balance Sheet'!C21)))-MAX(0,MIN('Balance Sheet'!C21,(((('Balance Sheet'!C7+D15)+D17)+D18)-'Assumptions'!B20)))) -> 6927.2679
A20: Cash from financing activities | B20: =(B18+B19) -> -4000 | C20: =(C18+C19) -> -507.52225 | D20: =(D18+D19) -> 2927.2679
A21: Net change in cash | B21: =((B15+B17)+B20) -> -528.15781 | C21: =((C15+C17)+C20) -> -971.84219 | D21: =((D15+D17)+D20) -> 0
A22: Beginning cash | B22: ='Assumptions'!B29 -> 9500 | C22: ='Balance Sheet'!B7 -> 8971.8422 | D22: ='Balance Sheet'!C7 -> 8000
A23: Ending cash | B23: =(B22+B21) -> 8971.8422 | C23: =(C22+C21) -> 8000 | D23: =(D22+D21) -> 8000
B26: FY2023 | C26: FY2024 | D26: FY2025
A27: Cash before revolver | B27: =((('Assumptions'!B29+B15)+B17)+B18) -> 8971.8422 | C27: =((('Balance Sheet'!B7+C15)+C17)+C18) -> 4507.5222 | D27: =((('Balance Sheet'!C7+D15)+D17)+D18) -> 1072.7321

Sheet Ratios
A1: Aldercrest Aerospace, Inc.
A2: Ratios
A3: ($ in thousands)
B5: FY2023 | C5: FY2024 | D5: FY2025
A6: Gross margin | B6: =('Income Statement'!B10/'Income Statement'!B8) -> 0.215 | C6: =('Income Statement'!C10/'Income Statement'!C8) -> 0.22 | D6: =('Income Statement'!D10/'Income Statement'!D8) -> 0.206
A7: EBITDA margin | B7: =('Income Statement'!B14/'Income Statement'!B8) -> 0.135 | C7: =('Income Statement'!C14/'Income Statement'!C8) -> 0.14 | D7: =('Income Statement'!D14/'Income Statement'!D8) -> 0.126
A8: Operating margin | B8: =('Income Statement'!B16/'Income Statement'!B8) -> 0.077215989 | C8: =('Income Statement'!C16/'Income Statement'!C8) -> 0.087997559 | D8: =('Income Statement'!D16/'Income Statement'!D8) -> 0.076695164
A9: Net margin | B9: =('Income Statement'!B20/'Income Statement'!B8) -> 0.041682749 | C9: =('Income Statement'!C20/'Income Statement'!C8) -> 0.053430921 | D9: =('Income Statement'!D20/'Income Statement'!D8) -> 0.046370047
A10: Revenue growth | B10: n/a | C10: =(('Income Statement'!C8/'Income Statement'!B8)-1) -> 0.14936886 | D10: =(('Income Statement'!D8/'Income Statement'!C8)-1) -> 0.12416107
A11: Current ratio | B11: =('Balance Sheet'!B12/'Balance Sheet'!B20) -> 2.6029013 | C11: =('Balance Sheet'!C12/'Balance Sheet'!C20) -> 2.553698 | D11: =('Balance Sheet'!D12/'Balance Sheet'!D20) -> 2.570755
A12: Debt to EBITDA | B12: =(('Balance Sheet'!B21+'Balance Sheet'!B22)/'Income Statement'!B14) -> 2.0778141 | C12: =(('Balance Sheet'!C21+'Balance Sheet'!C22)/'Income Statement'!C14) -> 1.7211051 | D12: =(('Balance Sheet'!D21+'Balance Sheet'!D22)/'Income Statement'!D14) -> 1.8272165
A13: Return on equity | B13: =('Income Statement'!B20/((('Assumptions'!B41+'Assumptions'!B42)+'Balance Sheet'!B27)/2)) -> 0.087190661 | C13: =('Income Statement'!C20/(('Balance Sheet'!B27+'Balance Sheet'!C27)/2)) -> 0.11595635 | D13: =('Income Statement'!D20/(('Balance Sheet'!C27+'Balance Sheet'!D27)/2)) -> 0.10150129
A14: Days sales outstanding | B14: =(('Balance Sheet'!B8/'Income Statement'!B8)*365) -> 48 | C14: =(('Balance Sheet'!C8/'Income Statement'!C8)*365) -> 48 | D14: =(('Balance Sheet'!D8/'Income Statement'!D8)*365) -> 48
A15: Days inventory outstanding | B15: =(('Balance Sheet'!B10/'Income Statement'!B9)*365) -> 62 | C15: =(('Balance Sheet'!C10/'Income Statement'!C9)*365) -> 62 | D15: =(('Balance Sheet'!D10/'Income Statement'!D9)*365) -> 62
A16: Days payable outstanding | B16: =(('Balance Sheet'!B17/'Income Statement'!B9)*365) -> 41 | C16: =(('Balance Sheet'!C17/'Income Statement'!C9)*365) -> 41 | D16: =(('Balance Sheet'!D17/'Income Statement'!D9)*365) -> 41
A17: Free cash flow | B17: =('Cash Flow'!B15+'Cash Flow'!B16) -> 3471.8422 | C17: =('Cash Flow'!C15+'Cash Flow'!C16) -> -464.31995 | D17: =('Cash Flow'!D15+'Cash Flow'!D16) -> -2927.2679
A18: FCF margin | B18: =(('Cash Flow'!B15+'Cash Flow'!B16)/'Income Statement'!B8) -> 0.024346719 | C18: =(('Cash Flow'!C15+'Cash Flow'!C16)/'Income Statement'!C8) -> -0.0028329466 | D18: =(('Cash Flow'!D15+'Cash Flow'!D16)/'Income Statement'!D8) -> -0.015887478

Sheet EVM
A1: Aldercrest Aerospace, Inc.
A2: Program ALX-7 earned value, FY2025
A3: ($ in thousands)
B5: Jan | C5: Feb | D5: Mar | E5: Apr | F5: May | G5: Jun | H5: Jul | I5: Aug | J5: Sep | K5: Oct | L5: Nov | M5: Dec
A6: Planned value (cumulative) | B6: =1100 -> 1100 | C6: =2400 -> 2400 | D6: =3900 -> 3900 | E6: =5600 -> 5600 | F6: =7500 -> 7500 | G6: =9600 -> 9600 | H6: =11900 -> 11900 | I6: =14300 -> 14300 | J6: =16800 -> 16800 | K6: =19400 -> 19400 | L6: =22000 -> 22000 | M6: =24600 -> 24600
A7: Earned value (cumulative) | B7: =1050 -> 1050 | C7: =2280 -> 2280 | D7: =3650 -> 3650 | E7: =5200 -> 5200 | F7: =6950 -> 6950 | G7: =8850 -> 8850 | H7: =10900 -> 10900 | I7: =13050 -> 13050 | J7: =15300 -> 15300 | K7: =17650 -> 17650 | L7: =20050 -> 20050 | M7: =22500 -> 22500
A8: Actual cost (cumulative) | B8: =1080 -> 1080 | C8: =2370 -> 2370 | D8: =3820 -> 3820 | E8: =5460 -> 5460 | F8: =7330 -> 7330 | G8: =9380 -> 9380 | H8: =11600 -> 11600 | I8: =13950 -> 13950 | J8: =16400 -> 16400 | K8: =18950 -> 18950 | L8: =21580 -> 21580 | M8: =24300 -> 24300
A9: Cost variance (EV - AC) | B9: =(B7-B8) -> -30 | C9: =(C7-C8) -> -90 | D9: =(D7-D8) -> -170 | E9: =(E7-E8) -> -260 | F9: =(F7-F8) -> -380 | G9: =(G7-G8) -> -530 | H9: =(H7-H8) -> -700 | I9: =(I7-I8) -> -900 | ... M9: =(M7-M8) -> -1800
A10: Schedule variance (EV - PV) | B10: =(B7-B6) -> -50 | C10: =(C7-C6) -> -120 | D10: =(D7-D6) -> -250 | E10: =(E7-E6) -> -400 | F10: =(F7-F6) -> -550 | G10: =(G7-G6) -> -750 | H10: =(H7-H6) -> -1000 | I10: =(I7-I6) -> -1250 | ... M10: =(M7-M6) -> -2100
A11: Cost performance index (CPI) | B11: =(B7/B8) -> 0.97222222 | C11: =(C7/C8) -> 0.96202532 | D11: =(D7/D8) -> 0.95549738 | E11: =(E7/E8) -> 0.95238095 | F11: =(F7/F8) -> 0.94815825 | G11: =(G7/G8) -> 0.9434968 | H11: =(H7/H8) -> 0.93965517 | I11: =(I7/I8) -> 0.93548387 | ... M11: =(M7/M8) -> 0.92592593
A12: Schedule performance index (SPI) | B12: =(B7/B6) -> 0.95454545 | C12: =(C7/C6) -> 0.95 | D12: =(D7/D6) -> 0.93589744 | E12: =(E7/E6) -> 0.92857143 | F12: =(F7/F6) -> 0.92666667 | G12: =(G7/G6) -> 0.921875 | H12: =(H7/H6) -> 0.91596639 | I12: =(I7/I6) -> 0.91258741 | ... M12: =(M7/M6) -> 0.91463415
B15: Value
A16: Budget at completion (BAC) | B16: =48000 -> 48000
A17: Planned value | B17: ='EVM'!M6 -> 24600
A18: Earned value | B18: ='EVM'!M7 -> 22500
A19: Actual cost | B19: ='EVM'!M8 -> 24300
A20: Cost variance (CV) | B20: =(B18-B19) -> -1800
A21: Schedule variance (SV) | B21: =(B18-B17) -> -2100
A22: Cost performance index (CPI) | B22: =(B18/B19) -> 0.92592593
A23: Schedule performance index (SPI) | B23: =(B18/B17) -> 0.91463415
A24: EAC using CPI (BAC / CPI) | B24: =(B16/B22) -> 51840
A25: EAC using CPI and SPI | B25: =(B19+((B16-B18)/(B22*B23))) -> 54410.4
A26: Estimate to complete | B26: =(B24-B19) -> 27540
A27: Variance at completion (BAC - EAC) | B27: =(B16-B24) -> -3840
A28: TCPI to BAC | B28: =((B16-B18)/(B16-B19)) -> 1.0759494
A29: Percent complete (EV / BAC) | B29: =(B18/B16) -> 0.46875
A30: Percent spent (AC / BAC) | B30: =(B19/B16) -> 0.50625

Sheet Contract
A1: Aldercrest Aerospace, Inc.
A2: Fixed price incentive contract economics
A3: ($ in thousands)
B5: Target cost | C5: EAC using CPI | D5: EAC using CPI and SPI
A6: Estimated cost | B6: =48000 -> 48000 | C6: ='EVM'!B24 -> 51840 | D6: ='EVM'!B25 -> 54410.4
A7: Fee | B7: =(MIN((B6+((48000*0.1)-(0.3*(B6-48000)))),(48000*1.2))-B6) -> 4800 | C7: =(MIN((C6+((48000*0.1)-(0.3*(C6-48000)))),(48000*1.2))-C6) -> 3648 | D7: =(MIN((D6+((48000*0.1)-(0.3*(D6-48000)))),(48000*1.2))-D6) -> 2876.88
A8: Price | B8: =MIN((B6+((48000*0.1)-(0.3*(B6-48000)))),(48000*1.2)) -> 52800 | C8: =MIN((C6+((48000*0.1)-(0.3*(C6-48000)))),(48000*1.2)) -> 55488 | D8: =MIN((D6+((48000*0.1)-(0.3*(D6-48000)))),(48000*1.2)) -> 57287.28
A9: Profit rate | B9: =(B7/B6) -> 0.1 | C9: =(C7/C6) -> 0.07037037 | D9: =(D7/D6) -> 0.052873715
A10: Distance to PTA | B10: =((48000+(((48000*1.2)-(48000+(48000*0.1)))/0.7))-B6) -> 6857.1429 | C10: =((48000+(((48000*1.2)-(48000+(48000*0.1)))/0.7))-C6) -> 3017.1429 | D10: =((48000+(((48000*1.2)-(48000+(48000*0.1)))/0.7))-D6) -> 446.74286
A11: Below the point of total assumption | B11: Yes | C11: Yes | D11: Yes
A13: Point of total assumption (PTA) | B13: =(48000+(((48000*1.2)-(48000+(48000*0.1)))/0.7)) -> 54857.143

Sheet Backlog
A1: Aldercrest Aerospace, Inc.
A2: Backlog and book to bill
A3: ($ in thousands)
B5: FY2023 | C5: FY2024 | D5: FY2025
A6: Beginning backlog | B6: ='Assumptions'!B44 -> 285000 | C6: =B9 -> 310800 | D6: =C9 -> 328100
A7: Bookings | B7: ='Assumptions'!B43 -> 168400 | C7: ='Assumptions'!C43 -> 181200 | D7: ='Assumptions'!D43 -> 171900
A8: Revenue | B8: ='Income Statement'!B8 -> 142600 | C8: ='Income Statement'!C8 -> 163900 | D8: ='Income Statement'!D8 -> 184250
A9: Ending backlog | B9: =((B6+B7)-B8) -> 310800 | C9: =((C6+C7)-C8) -> 328100 | D9: =((D6+D7)-D8) -> 315750
A10: Book to bill | B10: =(B7/B8) -> 1.1809257 | C10: =(C7/C8) -> 1.1055522 | D10: =(D7/D8) -> 0.93297151
A11: Backlog coverage, years | B11: =(B9/B8) -> 2.1795231 | C11: =(C9/C8) -> 2.0018304 | D11: =(D9/D8) -> 1.7137042

Sheet Checks
A1: Checks
A3: Overall status | B3: =IF(COUNTIF(C5:C28,"CHECK")=0,"ALL OK","CHECK FAILURES") -> ALL OK
A4: Check | B4: Difference | C4: Status
A5: Balance sheet balances, FY2023 | B5: =('Balance Sheet'!B15)-('Balance Sheet'!B28) -> 0 | C5: =IF(ABS(B5)<0.5,"OK","CHECK") -> OK
A6: Balance sheet balances, FY2024 | B6: =('Balance Sheet'!C15)-('Balance Sheet'!C28) -> 0 | C6: =IF(ABS(B6)<0.5,"OK","CHECK") -> OK
A7: Balance sheet balances, FY2025 | B7: =('Balance Sheet'!D15)-('Balance Sheet'!D28) -> 0 | C7: =IF(ABS(B7)<0.5,"OK","CHECK") -> OK
A8: Cash flow ending cash = balance sheet cash, FY2023 | B8: =('Cash Flow'!B23)-('Balance Sheet'!B7) -> 0 | C8: =IF(ABS(B8)<0.5,"OK","CHECK") -> OK
A9: Cash flow ending cash = balance sheet cash, FY2024 | B9: =('Cash Flow'!C23)-('Balance Sheet'!C7) -> 0 | C9: =IF(ABS(B9)<0.5,"OK","CHECK") -> OK
A10: Cash flow ending cash = balance sheet cash, FY2025 | B10: =('Cash Flow'!D23)-('Balance Sheet'!D7) -> 0 | C10: =IF(ABS(B10)<0.5,"OK","CHECK") -> OK
A11: Net income ties, income statement to cash flow, FY2023 | B11: =('Income Statement'!B20)-('Cash Flow'!B6) -> 0 | C11: =IF(ABS(B11)<0.5,"OK","CHECK") -> OK
A12: Net income ties, income statement to cash flow, FY2024 | B12: =('Income Statement'!C20)-('Cash Flow'!C6) -> 0 | C12: =IF(ABS(B12)<0.5,"OK","CHECK") -> OK
A13: Net income ties, income statement to cash flow, FY2025 | B13: =('Income Statement'!D20)-('Cash Flow'!D6) -> 0 | C13: =IF(ABS(B13)<0.5,"OK","CHECK") -> OK
A14: Beginning cash equals prior year ending cash, FY2023 | B14: =('Cash Flow'!B22)-('Assumptions'!B29) -> 0 | C14: =IF(ABS(B14)<0.5,"OK","CHECK") -> OK
A15: Beginning cash equals prior year ending cash, FY2024 | B15: =('Cash Flow'!C22)-('Cash Flow'!B23) -> 0 | C15: =IF(ABS(B15)<0.5,"OK","CHECK") -> OK
A16: Beginning cash equals prior year ending cash, FY2025 | B16: =('Cash Flow'!D22)-('Cash Flow'!C23) -> 0 | C16: =IF(ABS(B16)<0.5,"OK","CHECK") -> OK
A17: Retained earnings rolls forward, FY2023 | B17: =('Balance Sheet'!B26)-(('Assumptions'!B42+'Income Statement'!B20)) -> 0 | C17: =IF(ABS(B17)<0.5,"OK","CHECK") -> OK
A18: Retained earnings rolls forward, FY2024 | B18: =('Balance Sheet'!C26)-(('Balance Sheet'!B26+'Income Statement'!C20)) -> 0 | C18: =IF(ABS(B18)<0.5,"OK","CHECK") -> OK
A19: Retained earnings rolls forward, FY2025 | B19: =('Balance Sheet'!D26)-(('Balance Sheet'!C26+'Income Statement'!D20)) -> 0 | C19: =IF(ABS(B19)<0.5,"OK","CHECK") -> OK
A20: Total revenue equals its components, FY2023 | B20: =('Income Statement'!B8)-(('Income Statement'!B6+'Income Statement'!B7)) -> 0 | C20: =IF(ABS(B20)<0.5,"OK","CHECK") -> OK
A21: Total revenue equals its components, FY2024 | B21: =('Income Statement'!C8)-(('Income Statement'!C6+'Income Statement'!C7)) -> 0 | C21: =IF(ABS(B21)<0.5,"OK","CHECK") -> OK
A22: Total revenue equals its components, FY2025 | B22: =('Income Statement'!D8)-(('Income Statement'!D6+'Income Statement'!D7)) -> 0 | C22: =IF(ABS(B22)<0.5,"OK","CHECK") -> OK
A23: Total current assets equals its components, FY2023 | B23: =('Balance Sheet'!B12)-(('Balance Sheet'!B7+'Balance Sheet'!B8+'Balance Sheet'!B9+'Balance Sheet'!B10+'Balance Sheet'!B11)) -> 0 | C23: =IF(ABS(B23)<0.5,"OK","CHECK") -> OK
A24: Total current assets equals its components, FY2024 | B24: =('Balance Sheet'!C12)-(('Balance Sheet'!C7+'Balance Sheet'!C8+'Balance Sheet'!C9+'Balance Sheet'!C10+'Balance Sheet'!C11)) -> 0 | C24: =IF(ABS(B24)<0.5,"OK","CHECK") -> OK
A25: Total current assets equals its components, FY2025 | B25: =('Balance Sheet'!D12)-(('Balance Sheet'!D7+'Balance Sheet'!D8+'Balance Sheet'!D9+'Balance Sheet'!D10+'Balance Sheet'!D11)) -> 0 | C25: =IF(ABS(B25)<0.5,"OK","CHECK") -> OK
A26: Total liabilities equals its components, FY2023 | B26: =('Balance Sheet'!B23)-((('Balance Sheet'!B20+'Balance Sheet'!B21)+'Balance Sheet'!B22)) -> 0 | C26: =IF(ABS(B26)<0.5,"OK","CHECK") -> OK
A27: Total liabilities equals its components, FY2024 | B27: =('Balance Sheet'!C23)-((('Balance Sheet'!C20+'Balance Sheet'!C21)+'Balance Sheet'!C22)) -> 0 | C27: =IF(ABS(B27)<0.5,"OK","CHECK") -> OK
A28: Total liabilities equals its components, FY2025 | B28: =('Balance Sheet'!D23)-((('Balance Sheet'!D20+'Balance Sheet'!D21)+'Balance Sheet'!D22)) -> 0 | C28: =IF(ABS(B28)<0.5,"OK","CHECK") -> OK
