Workbook

Sheet Cover
A2: City of Palomar Vista, California
A4: General Fund budget and reserves for a city of 84,000
A6: Fiscal years covered: FY2023, FY2024, FY2025
A8: Industry: Local government
A9: Role fit: Budget analysis, Government finance
A10: Fiscal years end June 30 (FY2025 = July 1, 2024 to June 30, 2025).
A11: Governmental funds use modified accrual and report no cash flow statement.
A13: Fictional company. All figures are illustrative and were built for this portfolio.
A14: Prepared by George Murad
A16: Contents
A17: Cover
A18: Assumptions
... A29: Formula, pulls from another sheet

Sheet Assumptions
A1: City of Palomar Vista, California
A2: Assumptions
A3: ($ in thousands)
B5: FY2023 | C5: FY2024 | D5: FY2025
A6: Property taxes | B6: 38400 | C6: 40100 | D6: 41900
A7: Sales and use tax | B7: 22600 | C7: 23100 | D7: 22700
A8: Utility users tax | B8: 6100 | C8: 6300 | D8: 6450
A9: Transient occupancy tax | B9: 4200 | C9: 4650 | D9: 4900
A10: Franchise fees | B10: 3300 | C10: 3400 | D10: 3450
A11: Licenses and permits | B11: 2900 | C11: 3050 | D11: 2800
A12: Charges for services | B12: 5600 | C12: 5900 | D12: 6150
A13: Fines and forfeitures | B13: 900 | C13: 950 | D13: 920
A14: Investment earnings | B14: 450 | C14: 1650 | D14: 2100
A15: Intergovernmental | B15: 2200 | C15: 2100 | D15: 2050
A16: Other revenue | B16: 700 | C16: 650 | D16: 700
A17: General government | B17: 9600 | C17: 10100 | D17: 10500
... A25: Transfers out | B25: -2500 | C25: -3000 | D25: -2800
A26: Fund balance, July 1, 2022 | B26: 26800
A27: Receivables, % of total revenues | B27: 0.09
A28: Due from other funds | B28: 400 | C28: 450 | D28: 500
A29: Prepaid items | B29: 300 | C29: 320 | D29: 350
A30: Accounts payable, % of expenditures | B30: 0.05
A31: Accrued payroll, % of expenditures | B31: 0.03
A32: Unearned revenue | B32: 600 | C32: 650 | D32: 700
A33: Deposits | B33: 300 | C33: 300 | D33: 300
A34: Deferred inflows of resources (unavailable revenue) | B34: 800 | C34: 850 | D34: 900
A35: Committed (economic uncertainty reserve) | B35: 14000 | C35: 13500 | D35: 12000
A36: Assigned (capital replacement) | B36: 2500 | C36: 2000 | D36: 1500
A37: Reserve ratio policy minimum | B37: 0.17

Sheet Fund Activity
A1: City of Palomar Vista, California
A2: Statement of Revenues, Expenditures and Changes in Fund Balance, General Fund
A3: ($ in thousands) For the years ended June 30
B5: FY2023 | C5: FY2024 | D5: FY2025
A6: Revenues
A7: Property taxes | B7: ='Assumptions'!B6 -> 38400 | C7: ='Assumptions'!C6 -> 40100 | D7: ='Assumptions'!D6 -> 41900
A8: Sales and use tax | B8: ='Assumptions'!B7 -> 22600 | C8: ='Assumptions'!C7 -> 23100 | D8: ='Assumptions'!D7 -> 22700
A9: Utility users tax | B9: ='Assumptions'!B8 -> 6100 | C9: ='Assumptions'!C8 -> 6300 | D9: ='Assumptions'!D8 -> 6450
A10: Transient occupancy tax | B10: ='Assumptions'!B9 -> 4200 | C10: ='Assumptions'!C9 -> 4650 | D10: ='Assumptions'!D9 -> 4900
A11: Franchise fees | B11: ='Assumptions'!B10 -> 3300 | C11: ='Assumptions'!C10 -> 3400 | D11: ='Assumptions'!D10 -> 3450
A12: Licenses and permits | B12: ='Assumptions'!B11 -> 2900 | C12: ='Assumptions'!C11 -> 3050 | D12: ='Assumptions'!D11 -> 2800
A13: Charges for services | B13: ='Assumptions'!B12 -> 5600 | C13: ='Assumptions'!C12 -> 5900 | D13: ='Assumptions'!D12 -> 6150
A14: Fines and forfeitures | B14: ='Assumptions'!B13 -> 900 | C14: ='Assumptions'!C13 -> 950 | D14: ='Assumptions'!D13 -> 920
A15: Investment earnings | B15: ='Assumptions'!B14 -> 450 | C15: ='Assumptions'!C14 -> 1650 | D15: ='Assumptions'!D14 -> 2100
A16: Intergovernmental | B16: ='Assumptions'!B15 -> 2200 | C16: ='Assumptions'!C15 -> 2100 | D16: ='Assumptions'!D15 -> 2050
A17: Other revenue | B17: ='Assumptions'!B16 -> 700 | C17: ='Assumptions'!C16 -> 650 | D17: ='Assumptions'!D16 -> 700
A18: Total revenues | B18: =(B7+B8+B9+B10+B11+B12+B13+B14+B15+B16+B17) -> 87350 | C18: =(C7+C8+C9+C10+C11+C12+C13+C14+C15+C16+C17) -> 91850 | D18: =(D7+D8+D9+D10+D11+D12+D13+D14+D15+D16+D17) -> 94120
A19: Expenditures
A20: General government | B20: ='Assumptions'!B17 -> 9600 | C20: ='Assumptions'!C17 -> 10100 | D20: ='Assumptions'!D17 -> 10500
A21: Police | B21: ='Assumptions'!B18 -> 31500 | C21: ='Assumptions'!C18 -> 33400 | D21: ='Assumptions'!D18 -> 35600
A22: Fire | B22: ='Assumptions'!B19 -> 22100 | C22: ='Assumptions'!C19 -> 23500 | D22: ='Assumptions'!D19 -> 24900
A23: Public works | B23: ='Assumptions'!B20 -> 9800 | C23: ='Assumptions'!C20 -> 10200 | D23: ='Assumptions'!D20 -> 10700
A24: Parks and recreation | B24: ='Assumptions'!B21 -> 6900 | C24: ='Assumptions'!C21 -> 7200 | D24: ='Assumptions'!D21 -> 7600
A25: Community development | B25: ='Assumptions'!B22 -> 4300 | C25: ='Assumptions'!C22 -> 4500 | D25: ='Assumptions'!D22 -> 4700
A26: Nondepartmental | B26: ='Assumptions'!B23 -> 3200 | C26: ='Assumptions'!C23 -> 3500 | D26: ='Assumptions'!D23 -> 3900
A27: Total expenditures | B27: =(B20+B21+B22+B23+B24+B25+B26) -> 87400 | C27: =(C20+C21+C22+C23+C24+C25+C26) -> 92400 | D27: =(D20+D21+D22+D23+D24+D25+D26) -> 97900
A28: Excess (deficiency) of revenues over expenditures | B28: =(B18-B27) -> -50 | C28: =(C18-C27) -> -550 | D28: =(D18-D27) -> -3780
A29: Other financing sources (uses)
A30: Transfers in | B30: ='Assumptions'!B24 -> 1100 | C30: ='Assumptions'!C24 -> 1100 | D30: ='Assumptions'!D24 -> 1150
A31: Transfers out | B31: ='Assumptions'!B25 -> -2500 | C31: ='Assumptions'!C25 -> -3000 | D31: ='Assumptions'!D25 -> -2800
A32: Total other financing sources (uses) | B32: =(B30+B31) -> -1400 | C32: =(C30+C31) -> -1900 | D32: =(D30+D31) -> -1650
A33: Net change in fund balance | B33: =(B28+B32) -> -1450 | C33: =(C28+C32) -> -2450 | D33: =(D28+D32) -> -5430
A34: Fund balance, beginning | B34: ='Assumptions'!B26 -> 26800 | C34: =B35 -> 25350 | D34: =C35 -> 22900
A35: Fund balance, ending | B35: =(B34+B33) -> 25350 | C35: =(C34+C33) -> 22900 | D35: =(D34+D33) -> 17470

Sheet Fund Balance Sheet
A1: City of Palomar Vista, California
A2: Balance Sheet, General Fund
A3: ($ in thousands) As of June 30
B5: FY2023 | C5: FY2024 | D5: FY2025
A6: Assets
A7: Cash and investments | B7: =(((B26-B8)-B9)-B10) -> 25480.5 | C7: =(((C26-C8)-C9)-C10) -> 23055.5 | D7: =(((D26-D8)-D9)-D10) -> 17881.2
A8: Receivables | B8: =('Fund Activity'!B18*'Assumptions'!B27) -> 7861.5 | C8: =('Fund Activity'!C18*'Assumptions'!B27) -> 8266.5 | D8: =('Fund Activity'!D18*'Assumptions'!B27) -> 8470.8
A9: Due from other funds | B9: ='Assumptions'!B28 -> 400 | C9: ='Assumptions'!C28 -> 450 | D9: ='Assumptions'!D28 -> 500
A10: Prepaid items | B10: ='Assumptions'!B29 -> 300 | C10: ='Assumptions'!C29 -> 320 | D10: ='Assumptions'!D29 -> 350
A11: Total assets | B11: =(B7+B8+B9+B10) -> 34042 | C11: =(C7+C8+C9+C10) -> 32092 | D11: =(D7+D8+D9+D10) -> 27202
A12: Liabilities
A13: Accounts payable | B13: =('Fund Activity'!B27*'Assumptions'!B30) -> 4370 | C13: =('Fund Activity'!C27*'Assumptions'!B30) -> 4620 | D13: =('Fund Activity'!D27*'Assumptions'!B30) -> 4895
A14: Accrued payroll | B14: =('Fund Activity'!B27*'Assumptions'!B31) -> 2622 | C14: =('Fund Activity'!C27*'Assumptions'!B31) -> 2772 | D14: =('Fund Activity'!D27*'Assumptions'!B31) -> 2937
A15: Unearned revenue | B15: ='Assumptions'!B32 -> 600 | C15: ='Assumptions'!C32 -> 650 | D15: ='Assumptions'!D32 -> 700
A16: Deposits | B16: ='Assumptions'!B33 -> 300 | C16: ='Assumptions'!C33 -> 300 | D16: ='Assumptions'!D33 -> 300
A17: Total liabilities | B17: =(B13+B14+B15+B16) -> 7892 | C17: =(C13+C14+C15+C16) -> 8342 | D17: =(D13+D14+D15+D16) -> 8832
A18: Deferred inflows of resources
A19: Deferred inflows of resources (unavailable revenue) | B19: ='Assumptions'!B34 -> 800 | C19: ='Assumptions'!C34 -> 850 | D19: ='Assumptions'!D34 -> 900
A20: Fund balance
A21: Nonspendable | B21: =B10 -> 300 | C21: =C10 -> 320 | D21: =D10 -> 350
A22: Committed | B22: ='Assumptions'!B35 -> 14000 | C22: ='Assumptions'!C35 -> 13500 | D22: ='Assumptions'!D35 -> 12000
A23: Assigned | B23: ='Assumptions'!B36 -> 2500 | C23: ='Assumptions'!C36 -> 2000 | D23: ='Assumptions'!D36 -> 1500
A24: Unassigned | B24: =((('Fund Activity'!B35-B21)-B22)-B23) -> 8550 | C24: =((('Fund Activity'!C35-C21)-C22)-C23) -> 7080 | D24: =((('Fund Activity'!D35-D21)-D22)-D23) -> 3620
A25: Total fund balance | B25: =(B21+B22+B23+B24) -> 25350 | C25: =(C21+C22+C23+C24) -> 22900 | D25: =(D21+D22+D23+D24) -> 17470
A26: Total liabilities, deferred inflows and fund balance | B26: =((B17+B19)+B25) -> 34042 | C26: =((C17+C19)+C25) -> 32092 | D26: =((D17+D19)+D25) -> 27202
A27: Reserve ratio (committed plus unassigned / expenditures) | B27: =((B22+B24)/'Fund Activity'!B27) -> 0.25800915 | C27: =((C22+C24)/'Fund Activity'!C27) -> 0.22272727 | D27: =((D22+D24)/'Fund Activity'!D27) -> 0.15955056
A28: Reserve policy minimum | B28: ='Assumptions'!B37 -> 0.17 | C28: ='Assumptions'!B37 -> 0.17 | D28: ='Assumptions'!B37 -> 0.17
A29: Reserve policy minimum, dollars (17% of expenditures) | B29: =('Fund Activity'!B27*'Assumptions'!B37) -> 14858 | C29: =('Fund Activity'!C27*'Assumptions'!B37) -> 15708 | D29: =('Fund Activity'!D27*'Assumptions'!B37) -> 16643

Sheet Budget vs Actual
A1: City of Palomar Vista, California
A2: Budgetary Comparison, General Fund, FY2025
A3: ($ in thousands)
B5: Adopted | C5: Final | D5: Actual | E5: Variance | F5: Variance %
A6: Property taxes | B6: =41500 -> 41500 | C6: =41500 -> 41500 | D6: ='Fund Activity'!D7 -> 41900 | E6: =('Fund Activity'!D7-41500) -> 400 | F6: =(('Fund Activity'!D7-41500)/MAX(1,41500)) -> 0.0096385542
A7: Sales and use tax | B7: =23900 -> 23900 | C7: =23900 -> 23900 | D7: ='Fund Activity'!D8 -> 22700 | E7: =('Fund Activity'!D8-23900) -> -1200 | F7: =(('Fund Activity'!D8-23900)/MAX(1,23900)) -> -0.050209205
A8: Utility users tax | B8: =6400 -> 6400 | C8: =6400 -> 6400 | D8: ='Fund Activity'!D9 -> 6450 | E8: =('Fund Activity'!D9-6400) -> 50 | F8: =(('Fund Activity'!D9-6400)/MAX(1,6400)) -> 0.0078125
A9: Transient occupancy tax | B9: =4800 -> 4800 | C9: =4800 -> 4800 | D9: ='Fund Activity'!D10 -> 4900 | E9: =('Fund Activity'!D10-4800) -> 100 | F9: =(('Fund Activity'!D10-4800)/MAX(1,4800)) -> 0.020833333
A10: Franchise fees | B10: =3450 -> 3450 | C10: =3450 -> 3450 | D10: ='Fund Activity'!D11 -> 3450 | E10: =('Fund Activity'!D11-3450) -> 0 | F10: =(('Fund Activity'!D11-3450)/MAX(1,3450)) -> 0
A11: Licenses and permits | B11: =3100 -> 3100 | C11: =3100 -> 3100 | D11: ='Fund Activity'!D12 -> 2800 | E11: =('Fund Activity'!D12-3100) -> -300 | F11: =(('Fund Activity'!D12-3100)/MAX(1,3100)) -> -0.096774194
A12: Charges for services | B12: =6000 -> 6000 | C12: =6000 -> 6000 | D12: ='Fund Activity'!D13 -> 6150 | E12: =('Fund Activity'!D13-6000) -> 150 | F12: =(('Fund Activity'!D13-6000)/MAX(1,6000)) -> 0.025
A13: Fines and forfeitures | B13: =950 -> 950 | C13: =950 -> 950 | D13: ='Fund Activity'!D14 -> 920 | E13: =('Fund Activity'!D14-950) -> -30 | F13: =(('Fund Activity'!D14-950)/MAX(1,950)) -> -0.031578947
A14: Investment earnings | B14: =1200 -> 1200 | C14: =1200 -> 1200 | D14: ='Fund Activity'!D15 -> 2100 | E14: =('Fund Activity'!D15-1200) -> 900 | F14: =(('Fund Activity'!D15-1200)/MAX(1,1200)) -> 0.75
A15: Intergovernmental | B15: =2100 -> 2100 | C15: =2100 -> 2100 | D15: ='Fund Activity'!D16 -> 2050 | E15: =('Fund Activity'!D16-2100) -> -50 | F15: =(('Fund Activity'!D16-2100)/MAX(1,2100)) -> -0.023809524
A16: Other revenue | B16: =650 -> 650 | C16: =650 -> 650 | D16: ='Fund Activity'!D17 -> 700 | E16: =('Fund Activity'!D17-650) -> 50 | F16: =(('Fund Activity'!D17-650)/MAX(1,650)) -> 0.076923077
A17: Total revenues | B17: =(B6+B7+B8+B9+B10+B11+B12+B13+B14+B15+B16) -> 94050 | C17: =(C6+C7+C8+C9+C10+C11+C12+C13+C14+C15+C16) -> 94050 | D17: =(D6+D7+D8+D9+D10+D11+D12+D13+D14+D15+D16) -> 94120 | E17: =(D17-C17) -> 70 | F17: =(E17/C17) -> 0.00074428495
A18: General government | B18: =10800 -> 10800 | C18: =10800 -> 10800 | D18: ='Fund Activity'!D20 -> 10500 | E18: =(10800-'Fund Activity'!D20) -> 300 | F18: =((10800-'Fund Activity'!D20)/MAX(1,10800)) -> 0.027777778
A19: Police | B19: =33500 -> 33500 | C19: =34200 -> 34200 | D19: ='Fund Activity'!D21 -> 35600 | E19: =(34200-'Fund Activity'!D21) -> -1400 | F19: =((34200-'Fund Activity'!D21)/MAX(1,34200)) -> -0.040935673
A20: Fire | B20: =24600 -> 24600 | C20: =24600 -> 24600 | D20: ='Fund Activity'!D22 -> 24900 | E20: =(24600-'Fund Activity'!D22) -> -300 | F20: =((24600-'Fund Activity'!D22)/MAX(1,24600)) -> -0.012195122
A21: Public works | B21: =11400 -> 11400 | C21: =11400 -> 11400 | D21: ='Fund Activity'!D23 -> 10700 | E21: =(11400-'Fund Activity'!D23) -> 700 | F21: =((11400-'Fund Activity'!D23)/MAX(1,11400)) -> 0.061403509
A22: Parks and recreation | B22: =7700 -> 7700 | C22: =7700 -> 7700 | D22: ='Fund Activity'!D24 -> 7600 | E22: =(7700-'Fund Activity'!D24) -> 100 | F22: =((7700-'Fund Activity'!D24)/MAX(1,7700)) -> 0.012987013
A23: Community development | B23: =5000 -> 5000 | C23: =5000 -> 5000 | D23: ='Fund Activity'!D25 -> 4700 | E23: =(5000-'Fund Activity'!D25) -> 300 | F23: =((5000-'Fund Activity'!D25)/MAX(1,5000)) -> 0.06
A24: Nondepartmental | B24: =3900 -> 3900 | C24: =3900 -> 3900 | D24: ='Fund Activity'!D26 -> 3900 | E24: =(3900-'Fund Activity'!D26) -> 0 | F24: =((3900-'Fund Activity'!D26)/MAX(1,3900)) -> 0
A25: Total expenditures | B25: =(B18+B19+B20+B21+B22+B23+B24) -> 96900 | C25: =(C18+C19+C20+C21+C22+C23+C24) -> 97600 | D25: =(D18+D19+D20+D21+D22+D23+D24) -> 97900 | E25: =(C25-D25) -> -300 | F25: =(E25/C25) -> -0.0030737705
A26: Transfers in | B26: =1150 -> 1150 | C26: =1150 -> 1150 | D26: ='Fund Activity'!D30 -> 1150 | E26: =('Fund Activity'!D30-1150) -> 0 | F26: =(('Fund Activity'!D30-1150)/MAX(1,1150)) -> 0
A27: Transfers out | B27: =-2800 -> -2800 | C27: =-2800 -> -2800 | D27: ='Fund Activity'!D31 -> -2800 | E27: =('Fund Activity'!D31--2800) -> 0 | F27: =(('Fund Activity'!D31--2800)/MAX(1,(--2800))) -> 0
A28: Net change in fund balance | B28: =(((B17-B25)+B26)+B27) -> -4500 | C28: =(((C17-C25)+C26)+C27) -> -5200 | D28: =(((D17-D25)+D26)+D27) -> -5430 | E28: =(D28-C28) -> -230 | F28: =(E28/(-C28)) -> -0.044230769

Sheet Forecast
A1: City of Palomar Vista, California
A2: Five year forecast with no corrective action
A3: ($ in thousands)
B5: FY2026 | C5: FY2027 | D5: FY2028 | E5: FY2029 | F5: FY2030
A6: Property taxes | B6: =('Fund Activity'!D7*(1+0.04)) -> 43576 | C6: =(B6*(1+0.04)) -> 45319.04 | D6: =(C6*(1+0.04)) -> 47131.802 | E6: =(D6*(1+0.04)) -> 49017.074 | F6: =(E6*(1+0.04)) -> 50977.757
A7: Sales and use tax | B7: =('Fund Activity'!D8*(1+0.015)) -> 23040.5 | C7: =(B7*(1+0.015)) -> 23386.107 | D7: =(C7*(1+0.015)) -> 23736.899 | E7: =(D7*(1+0.015)) -> 24092.953 | F7: =(E7*(1+0.015)) -> 24454.347
A8: Utility users tax | B8: =('Fund Activity'!D9*(1+0.02)) -> 6579 | C8: =(B8*(1+0.02)) -> 6710.58 | D8: =(C8*(1+0.02)) -> 6844.7916 | E8: =(D8*(1+0.02)) -> 6981.6874 | F8: =(E8*(1+0.02)) -> 7121.3212
A9: Transient occupancy tax | B9: =('Fund Activity'!D10*(1+0.03)) -> 5047 | C9: =(B9*(1+0.03)) -> 5198.41 | D9: =(C9*(1+0.03)) -> 5354.3623 | E9: =(D9*(1+0.03)) -> 5514.9932 | F9: =(E9*(1+0.03)) -> 5680.443
A10: Franchise fees | B10: =('Fund Activity'!D11*(1+0.02)) -> 3519 | C10: =(B10*(1+0.02)) -> 3589.38 | D10: =(C10*(1+0.02)) -> 3661.1676 | E10: =(D10*(1+0.02)) -> 3734.391 | F10: =(E10*(1+0.02)) -> 3809.0788
A11: Licenses and permits | B11: =('Fund Activity'!D12*(1+0.02)) -> 2856 | C11: =(B11*(1+0.02)) -> 2913.12 | D11: =(C11*(1+0.02)) -> 2971.3824 | E11: =(D11*(1+0.02)) -> 3030.81 | F11: =(E11*(1+0.02)) -> 3091.4262
A12: Charges for services | B12: =('Fund Activity'!D13*(1+0.03)) -> 6334.5 | C12: =(B12*(1+0.03)) -> 6524.535 | D12: =(C12*(1+0.03)) -> 6720.2711 | E12: =(D12*(1+0.03)) -> 6921.8792 | F12: =(E12*(1+0.03)) -> 7129.5356
A13: Fines and forfeitures | B13: =('Fund Activity'!D14*(1+0)) -> 920 | C13: =(B13*(1+0)) -> 920 | D13: =(C13*(1+0)) -> 920 | E13: =(D13*(1+0)) -> 920 | F13: =(E13*(1+0)) -> 920
A14: Investment earnings | B14: =1900 -> 1900 | C14: =1700 -> 1700 | D14: =1600 -> 1600 | E14: =1600 -> 1600 | F14: =1600 -> 1600
A15: Intergovernmental | B15: =('Fund Activity'!D16*(1+0.01)) -> 2070.5 | C15: =(B15*(1+0.01)) -> 2091.205 | D15: =(C15*(1+0.01)) -> 2112.117 | E15: =(D15*(1+0.01)) -> 2133.2382 | F15: =(E15*(1+0.01)) -> 2154.5706
A16: Other revenue | B16: =('Fund Activity'!D17*(1+0.02)) -> 714 | C16: =(B16*(1+0.02)) -> 728.28 | D16: =(C16*(1+0.02)) -> 742.8456 | E16: =(D16*(1+0.02)) -> 757.70251 | F16: =(E16*(1+0.02)) -> 772.85656
A17: Total revenues | B17: =(B6+B7+B8+B9+B10+B11+B12+B13+B14+B15+B16) -> 96556.5 | C17: =(C6+C7+C8+C9+C10+C11+C12+C13+C14+C15+C16) -> 99080.658 | D17: =(D6+D7+D8+D9+D10+D11+D12+D13+D14+D15+D16) -> 101795.64 | E17: =(E6+E7+E8+E9+E10+E11+E12+E13+E14+E15+E16) -> 104704.73 | F17: =(F6+F7+F8+F9+F10+F11+F12+F13+F14+F15+F16) -> 107711.34
A18: General government | B18: =('Fund Activity'!D20*(1+0.033)) -> 10846.5 | C18: =(B18*(1+0.033)) -> 11204.434 | D18: =(C18*(1+0.033)) -> 11574.181 | E18: =(D18*(1+0.033)) -> 11956.129 | F18: =(E18*(1+0.033)) -> 12350.681
A19: Police | B19: =('Fund Activity'!D21*(1+0.033)) -> 36774.8 | C19: =(B19*(1+0.033)) -> 37988.368 | D19: =(C19*(1+0.033)) -> 39241.985 | E19: =(D19*(1+0.033)) -> 40536.97 | F19: =(E19*(1+0.033)) -> 41874.69
A20: Fire | B20: =('Fund Activity'!D22*(1+0.033)) -> 25721.7 | C20: =(B20*(1+0.033)) -> 26570.516 | D20: =(C20*(1+0.033)) -> 27447.343 | E20: =(D20*(1+0.033)) -> 28353.105 | F20: =(E20*(1+0.033)) -> 29288.758
A21: Public works | B21: =('Fund Activity'!D23*(1+0.033)) -> 11053.1 | C21: =(B21*(1+0.033)) -> 11417.852 | D21: =(C21*(1+0.033)) -> 11794.641 | E21: =(D21*(1+0.033)) -> 12183.865 | F21: =(E21*(1+0.033)) -> 12585.932
A22: Parks and recreation | B22: =('Fund Activity'!D24*(1+0.033)) -> 7850.8 | C22: =(B22*(1+0.033)) -> 8109.8764 | D22: =(C22*(1+0.033)) -> 8377.5023 | E22: =(D22*(1+0.033)) -> 8653.9599 | F22: =(E22*(1+0.033)) -> 8939.5406
A23: Community development | B23: =('Fund Activity'!D25*(1+0.033)) -> 4855.1 | C23: =(B23*(1+0.033)) -> 5015.3183 | D23: =(C23*(1+0.033)) -> 5180.8238 | E23: =(D23*(1+0.033)) -> 5351.791 | F23: =(E23*(1+0.033)) -> 5528.4001
A24: Nondepartmental | B24: =('Fund Activity'!D26*(1+0.08)) -> 4212 | C24: =(B24*(1+0.08)) -> 4548.96 | D24: =(C24*(1+0.08)) -> 4912.8768 | E24: =(D24*(1+0.08)) -> 5305.9069 | F24: =(E24*(1+0.08)) -> 5730.3795
A25: Total expenditures | B25: =(B18+B19+B20+B21+B22+B23+B24) -> 101314 | C25: =(C18+C19+C20+C21+C22+C23+C24) -> 104855.33 | D25: =(D18+D19+D20+D21+D22+D23+D24) -> 108529.35 | E25: =(E18+E19+E20+E21+E22+E23+E24) -> 112341.73 | F25: =(F18+F19+F20+F21+F22+F23+F24) -> 116298.38
A26: Operating result | B26: =(B17-B25) -> -4757.5 | C26: =(C17-C25) -> -5774.6685 | D26: =(D17-D25) -> -6733.7146 | E26: =(E17-E25) -> -7636.999 | F26: =(F17-F25) -> -8587.046
A27: Net transfers | B27: =-1650 -> -1650 | C27: =-1650 -> -1650 | D27: =-1650 -> -1650 | E27: =-1650 -> -1650 | F27: =-1650 -> -1650
A28: Net change in fund balance | B28: =(B26+B27) -> -6407.5 | C28: =(C26+C27) -> -7424.6685 | D28: =(D26+D27) -> -8383.7146 | E28: =(E26+E27) -> -9286.999 | F28: =(F26+F27) -> -10237.046
A29: Ending fund balance | B29: =('Fund Activity'!D35+B28) -> 11062.5 | C29: =(B29+C28) -> 3637.8315 | D29: =(C29+D28) -> -4745.8831 | E29: =(D29+E28) -> -14032.882 | F29: =(E29+F28) -> -24269.928
A30: Reserve ratio | B30: =((B29-1850)/B25) -> 0.090930177 | C30: =((C29-1850)/C25) -> 0.01705046 | D30: =((D29-1850)/D25) -> -0.060775107 | E30: =((E29-1850)/E25) -> -0.14138008 | F30: =((F29-1850)/F25) -> -0.22459408
A31: Policy minimum (17% of expenditures) | B31: =(B25*'Assumptions'!B37) -> 17223.38 | C31: =(C25*'Assumptions'!B37) -> 17825.405 | D31: =(D25*'Assumptions'!B37) -> 18449.99 | E31: =(E25*'Assumptions'!B37) -> 19098.094 | F31: =(F25*'Assumptions'!B37) -> 19770.725

Sheet Options
A1: City of Palomar Vista, California
A2: Options to close the gap, FY2026
A3: ($ in thousands)
B5: Amount
A6: Hold 12 vacant civilian positions | B6: =1600 -> 1600
A7: Update fees to recover full cost | B7: =900 -> 900
A8: Raise transient occupancy tax from 10% to 12% (needs voter approval) | B8: =980 -> 980
A9: Defer capital transfer for two years | B9: =1000 -> 1000
A10: Prepay pension payments early for the discount | B10: =150 -> 150
A11: Total, all options | B11: =(B6+B7+B8+B9+B10) -> 4630
A12: FY2026 forecast gap (operating result + net transfers) | B12: ='Forecast'!B28 -> -6407.5
A13: Remaining gap after options | B13: =(B12+B11) -> -1777.5

Sheet Checks
A1: Checks
A3: Overall status | B3: =IF(COUNTIF(C5:C22,"CHECK")=0,"ALL OK","CHECK FAILURES") -> ALL OK
A4: Check | B4: Difference | C4: Status
A5: Assets equal liabilities, deferred inflows and fund balance (construction check), FY2023 | B5: =('Fund Balance Sheet'!B11)-('Fund Balance Sheet'!B26) -> 0 | C5: =IF(ABS(B5)<0.5,"OK","CHECK") -> OK
A6: Assets equal liabilities, deferred inflows and fund balance (construction check), FY2024 | B6: =('Fund Balance Sheet'!C11)-('Fund Balance Sheet'!C26) -> 0 | C6: =IF(ABS(B6)<0.5,"OK","CHECK") -> OK
A7: Assets equal liabilities, deferred inflows and fund balance (construction check), FY2025 | B7: =('Fund Balance Sheet'!D11)-('Fund Balance Sheet'!D26) -> 0 | C7: =IF(ABS(B7)<0.5,"OK","CHECK") -> OK
A8: Balance sheet fund balance equals Fund Activity ending fund balance, FY2023 | B8: =('Fund Balance Sheet'!B25)-('Fund Activity'!B35) -> 0 | C8: =IF(ABS(B8)<0.5,"OK","CHECK") -> OK
A9: Balance sheet fund balance equals Fund Activity ending fund balance, FY2024 | B9: =('Fund Balance Sheet'!C25)-('Fund Activity'!C35) -> 0 | C9: =IF(ABS(B9)<0.5,"OK","CHECK") -> OK
A10: Balance sheet fund balance equals Fund Activity ending fund balance, FY2025 | B10: =('Fund Balance Sheet'!D25)-('Fund Activity'!D35) -> 0 | C10: =IF(ABS(B10)<0.5,"OK","CHECK") -> OK
A11: Fund balance beginning equals prior year ending, FY2023 | B11: =('Fund Activity'!B34)-('Assumptions'!B26) -> 0 | C11: =IF(ABS(B11)<0.5,"OK","CHECK") -> OK
A12: Fund balance beginning equals prior year ending, FY2024 | B12: =('Fund Activity'!C34)-('Fund Activity'!B35) -> 0 | C12: =IF(ABS(B12)<0.5,"OK","CHECK") -> OK
A13: Fund balance beginning equals prior year ending, FY2025 | B13: =('Fund Activity'!D34)-('Fund Activity'!C35) -> 0 | C13: =IF(ABS(B13)<0.5,"OK","CHECK") -> OK
A14: Total revenues equal their components, FY2023 | B14: =('Fund Activity'!B18)-(('Fund Activity'!B7+'Fund Activity'!B8+'Fund Activity'!B9+'Fund Activity'!B10+'Fund Activity'!B11+'Fund Activity'!B12+'Fund Activity'!B13+'Fund Activity'!B14+'Fund Activity'!B15+'Fund Activity'!B16+'Fund Activity'!B17)) -> 0 | C14: =IF(ABS(B14)<0.5,"OK","CHECK") -> OK
A15: Total revenues equal their components, FY2024 | B15: =('Fund Activity'!C18)-(('Fund Activity'!C7+'Fund Activity'!C8+'Fund Activity'!C9+'Fund Activity'!C10+'Fund Activity'!C11+'Fund Activity'!C12+'Fund Activity'!C13+'Fund Activity'!C14+'Fund Activity'!C15+'Fund Activity'!C16+'Fund Activity'!C17)) -> 0 | C15: =IF(ABS(B15)<0.5,"OK","CHECK") -> OK
A16: Total revenues equal their components, FY2025 | B16: =('Fund Activity'!D18)-(('Fund Activity'!D7+'Fund Activity'!D8+'Fund Activity'!D9+'Fund Activity'!D10+'Fund Activity'!D11+'Fund Activity'!D12+'Fund Activity'!D13+'Fund Activity'!D14+'Fund Activity'!D15+'Fund Activity'!D16+'Fund Activity'!D17)) -> 0 | C16: =IF(ABS(B16)<0.5,"OK","CHECK") -> OK
A17: Total expenditures equal their components, FY2023 | B17: =('Fund Activity'!B27)-(('Fund Activity'!B20+'Fund Activity'!B21+'Fund Activity'!B22+'Fund Activity'!B23+'Fund Activity'!B24+'Fund Activity'!B25+'Fund Activity'!B26)) -> 0 | C17: =IF(ABS(B17)<0.5,"OK","CHECK") -> OK
A18: Total expenditures equal their components, FY2024 | B18: =('Fund Activity'!C27)-(('Fund Activity'!C20+'Fund Activity'!C21+'Fund Activity'!C22+'Fund Activity'!C23+'Fund Activity'!C24+'Fund Activity'!C25+'Fund Activity'!C26)) -> 0 | C18: =IF(ABS(B18)<0.5,"OK","CHECK") -> OK
A19: Total expenditures equal their components, FY2025 | B19: =('Fund Activity'!D27)-(('Fund Activity'!D20+'Fund Activity'!D21+'Fund Activity'!D22+'Fund Activity'!D23+'Fund Activity'!D24+'Fund Activity'!D25+'Fund Activity'!D26)) -> 0 | C19: =IF(ABS(B19)<0.5,"OK","CHECK") -> OK
A20: Cash and investments is positive, FY2023 | B20: =('Fund Balance Sheet'!B7)-(MAX('Fund Balance Sheet'!B7,0)) -> 0 | C20: =IF(ABS(B20)<0.5,"OK","CHECK") -> OK
A21: Cash and investments is positive, FY2024 | B21: =('Fund Balance Sheet'!C7)-(MAX('Fund Balance Sheet'!C7,0)) -> 0 | C21: =IF(ABS(B21)<0.5,"OK","CHECK") -> OK
A22: Cash and investments is positive, FY2025 | B22: =('Fund Balance Sheet'!D7)-(MAX('Fund Balance Sheet'!D7,0)) -> 0 | C22: =IF(ABS(B22)<0.5,"OK","CHECK") -> OK
